Workbook
Name Slicer_Order_Status: #N/A
Name Slicer_Payment_Method: #N/A

Sheet Raw_Orders
A1: Order_ID | B1: Order_Date | C1: Customer_ID | D1: Customer_Name | E1: Restaurant_ID | F1: Restaurant Name | G1: Food_ID | H1: Food Name | I1: Food Price | J1: Delivery_Partner_ID | K1: Delivery Partner Name | L1: Quantity | M1: Order_Status | N1: Payment_Method | O1: Delivery_Time_Min | P1: Total Amount | Q1: Delivery Performance | S1: SUMIF
A2: O00001 | B2: 45942 | C2: C0359 | D2: {=_xlfn.XLOOKUP(C2,Customers!A:A,Customers!B:B)} -> Customer 0359 | E2: R079 | F2: {=_xlfn.XLOOKUP(E2,Restaurants!A:A,Restaurants!B:B)} -> Restaurant 079 | G2: F0016 | H2: {=_xlfn.XLOOKUP(G2,Food_Menu!A:A,Food_Menu!B:B)} -> Food Item 0016 | I2: {=_xlfn.XLOOKUP(G2,Food_Menu!A:A,Food_Menu!D:D)} -> 348.44 | J2: D163 | K2: {=_xlfn.XLOOKUP(J2,Delivery_Partners!A:A,Delivery_Partners!B:B)} -> Delivery Partner 163 | L2: 1 | M2: Delivered | N2: UPI | O2: 35 | P2: =I2*L2 -> 348.44 | Q2: =IF(O2="","Not Delivered",IF(O2<=30,"Fast",IF(O2<=60,"Normal","Slow"))) -> Normal | S2: =SUMIFS(P2:P8001,M2:M8001,"Delivered",N2:N8001,"UPI") -> 2187388.1
A3: O00002 | B3: 45840 | C3: C0231 | D3: {=_xlfn.XLOOKUP(C3,Customers!A:A,Customers!B:B)} -> Customer 0231 | E3: R033 | F3: {=_xlfn.XLOOKUP(E3,Restaurants!A:A,Restaurants!B:B)} -> Restaurant 033 | G3: F0057 | H3: {=_xlfn.XLOOKUP(G3,Food_Menu!A:A,Food_Menu!B:B)} -> Food Item 0057 | I3: {=_xlfn.XLOOKUP(G3,Food_Menu!A:A,Food_Menu!D:D)} -> 302.55 | J3: D017 | K3: {=_xlfn.XLOOKUP(J3,Delivery_Partners!A:A,Delivery_Partners!B:B)} -> Delivery Partner 017 | L3: 4 | M3: Delivered | N3: UPI | O3: 32 | P3: =I3*L3 -> 1210.2 | Q3: =IF(O3="","Not Delivered",IF(O3<=30,"Fast",IF(O3<=60,"Normal","Slow"))) -> Normal
A4: O00003 | B4: 25/08/2025 | C4: C0107 | D4: {=_xlfn.XLOOKUP(C4,Customers!A:A,Customers!B:B)} -> Customer 0107 | E4: R035 | F4: {=_xlfn.XLOOKUP(E4,Restaurants!A:A,Restaurants!B:B)} -> Restaurant 035 | G4: F0177 | H4: {=_xlfn.XLOOKUP(G4,Food_Menu!A:A,Food_Menu!B:B)} -> Food Item 0177 | I4: {=_xlfn.XLOOKUP(G4,Food_Menu!A:A,Food_Menu!D:D)} -> 268.83 | J4: D081 | K4: {=_xlfn.XLOOKUP(J4,Delivery_Partners!A:A,Delivery_Partners!B:B)} -> Delivery Partner 081 | L4: 3 | M4: Delivered | N4: UPI | O4: 44 | P4: =I4*L4 -> 806.49 | Q4: =IF(O4="","Not Delivered",IF(O4<=30,"Fast",IF(O4<=60,"Normal","Slow"))) -> Normal | S4: COUNTIFS
A5: O00004 | B5: 45912 | C5: C0768 | D5: {=_xlfn.XLOOKUP(C5,Customers!A:A,Customers!B:B)} -> Customer 0768 | E5: R077 | F5: {=_xlfn.XLOOKUP(E5,Restaurants!A:A,Restaurants!B:B)} -> Restaurant 077 | G5: F0134 | H5: {=_xlfn.XLOOKUP(G5,Food_Menu!A:A,Food_Menu!B:B)} -> Food Item 0134 | I5: {=_xlfn.XLOOKUP(G5,Food_Menu!A:A,Food_Menu!D:D)} -> 467.29 | J5: D041 | K5: {=_xlfn.XLOOKUP(J5,Delivery_Partners!A:A,Delivery_Partners!B:B)} -> Delivery Partner 041 | L5: 1 | M5: Delivered | N5: Cash | O5: 36 | P5: =I5*L5 -> 467.29 | Q5: =IF(O5="","Not Delivered",IF(O5<=30,"Fast",IF(O5<=60,"Normal","Slow"))) -> Normal | S5: =COUNTIFS(M2:M8001,"Delivered",N2:N8001,"UPI") -> 3580
A6: O00005 | B6: 28/04/2025 | C6: C1152 | D6: {=_xlfn.XLOOKUP(C6,Customers!A:A,Customers!B:B)} -> Customer 1152 | E6: R043 | F6: {=_xlfn.XLOOKUP(E6,Restaurants!A:A,Restaurants!B:B)} -> Restaurant 043 | G6: F0056 | H6: {=_xlfn.XLOOKUP(G6,Food_Menu!A:A,Food_Menu!B:B)} -> Food Item 0056 | I6: {=_xlfn.XLOOKUP(G6,Food_Menu!A:A,Food_Menu!D:D)} -> 536.41 | J6: D119 | K6: {=_xlfn.XLOOKUP(J6,Delivery_Partners!A:A,Delivery_Partners!B:B)} -> Delivery Partner 119 | L6: 2 | M6: Delivered | N6: UPI | O6: 42 | P6: =I6*L6 -> 1072.82 | Q6: =IF(O6="","Not Delivered",IF(O6<=30,"Fast",IF(O6<=60,"Normal","Slow"))) -> Normal
A7: O00006 | B7: 25/01/2025 | C7: C0097 | D7: {=_xlfn.XLOOKUP(C7,Customers!A:A,Customers!B:B)} -> Customer 0097 | E7: R083 | F7: {=_xlfn.XLOOKUP(E7,Restaurants!A:A,Restaurants!B:B)} -> Restaurant 083 | G7: F0205 | H7: {=_xlfn.XLOOKUP(G7,Food_Menu!A:A,Food_Menu!B:B)} -> Food Item 0205 | I7: {=_xlfn.XLOOKUP(G7,Food_Menu!A:A,Food_Menu!D:D)} -> 175.36 | J7: D075 | K7: {=_xlfn.XLOOKUP(J7,Delivery_Partners!A:A,Delivery_Partners!B:B)} -> Delivery Partner 075 | L7: 2 | M7: Delivered | N7: Card | O7: 39 | P7: =I7*L7 -> 350.72 | Q7: =IF(O7="","Not Delivered",IF(O7<=30,"Fast",IF(O7<=60,"Normal","Slow"))) -> Normal | S7: AVERAGEIFS
A8: O00007 | B8: 16/11/2025 | C8: C0844 | D8: {=_xlfn.XLOOKUP(C8,Customers!A:A,Customers!B:B)} -> Customer 0844 | E8: R019 | F8: {=_xlfn.XLOOKUP(E8,Restaurants!A:A,Restaurants!B:B)} -> Restaurant 019 | G8: F0168 | H8: {=_xlfn.XLOOKUP(G8,Food_Menu!A:A,Food_Menu!B:B)} -> Food Item 0168 | I8: {=_xlfn.XLOOKUP(G8,Food_Menu!A:A,Food_Menu!D:D)} -> 107.01 | J8: D051 | K8: {=_xlfn.XLOOKUP(J8,Delivery_Partners!A:A,Delivery_Partners!B:B)} -> Delivery Partner 051 | L8: 1 | M8: Delivered | N8: UPI | O8: 42 | P8: =I8*L8 -> 107.01 | Q8: =IF(O8="","Not Delivered",IF(O8<=30,"Fast",IF(O8<=60,"Normal","Slow"))) -> Normal | S8: =AVERAGEIFS(O2:O8001,M2:M8001,"Delivered",N2:N8001,"UPI") -> 35.259497
A9: O00008 | B9: 23/06/2025 | C9: C0702 | D9: {=_xlfn.XLOOKUP(C9,Customers!A:A,Customers!B:B)} -> Customer 0702 | E9: R037 | F9: {=_xlfn.XLOOKUP(E9,Restaurants!A:A,Restaurants!B:B)} -> Restaurant 037 | G9: F0172 | H9: {=_xlfn.XLOOKUP(G9,Food_Menu!A:A,Food_Menu!B:B)} -> Food Item 0172 | I9: {=_xlfn.XLOOKUP(G9,Food_Menu!A:A,Food_Menu!D:D)} -> 219.12 | J9: D046 | K9: {=_xlfn.XLOOKUP(J9,Delivery_Partners!A:A,Delivery_Partners!B:B)} -> Delivery Partner 046 | L9: 2 | M9: Delivered | N9: UPI | O9: 30 | P9: =I9*L9 -> 438.24 | Q9: =IF(O9="","Not Delivered",IF(O9<=30,"Fast",IF(O9<=60,"Normal","Slow"))) -> Fast
A10: O00009 | B10: 45931 | C10: C0207 | D10: {=_xlfn.XLOOKUP(C10,Customers!A:A,Customers!B:B)} -> Customer 0207 | E10: R013 | F10: {=_xlfn.XLOOKUP(E10,Restaurants!A:A,Restaurants!B:B)} -> Restaurant 013 | G10: F0198 | H10: {=_xlfn.XLOOKUP(G10,Food_Menu!A:A,Food_Menu!B:B)} -> Food Item 0198 | I10: {=_xlfn.XLOOKUP(G10,Food_Menu!A:A,Food_Menu!D:D)} -> 221.88 | J10: D064 | K10: {=_xlfn.XLOOKUP(J10,Delivery_Partners!A:A,Delivery_Partners!B:B)} -> Delivery Partner 064 | L10: 3 | M10: Delivered | N10: Wallet | O10: 48 | P10: =I10*L10 -> 665.64 | Q10: =IF(O10="","Not Delivered",IF(O10<=30,"Fast",IF(O10<=60,"Normal","Slow"))) -> Normal | S10: INDEX + MATCH
A11: O00010 | B11: 45727 | C11: C0256 | D11: {=_xlfn.XLOOKUP(C11,Customers!A:A,Customers!B:B)} -> Customer 0256 | E11: R011 | F11: {=_xlfn.XLOOKUP(E11,Restaurants!A:A,Restaurants!B:B)} -> Restaurant 011 | G11: F0165 | H11: {=_xlfn.XLOOKUP(G11,Food_Menu!A:A,Food_Menu!B:B)} -> Food Item 0165 | I11: {=_xlfn.XLOOKUP(G11,Food_Menu!A:A,Food_Menu!D:D)} -> 508.61 | J11: D020 | K11: {=_xlfn.XLOOKUP(J11,Delivery_Partners!A:A,Delivery_Partners!B:B)} -> Delivery Partner 020 | L11: 1 | M11: Delivered | N11: UPI | O11: 20 | P11: =I11*L11 -> 508.61 | Q11: =IF(O11="","Not Delivered",IF(O11<=30,"Fast",IF(O11<=60,"Normal","Slow"))) -> Fast | S11: {=INDEX(Food_Menu!D:D,MATCH(G2,Food_Menu!A:A,0))} -> 348.44
A12: O00011 | B12: 45786 | C12: C0342 | D12: {=_xlfn.XLOOKUP(C12,Customers!A:A,Customers!B:B)} -> Customer 0342 | E12: R032 | F12: {=_xlfn.XLOOKUP(E12,Restaurants!A:A,Restaurants!B:B)} -> Restaurant 032 | G12: F0211 | H12: {=_xlfn.XLOOKUP(G12,Food_Menu!A:A,Food_Menu!B:B)} -> Food Item 0211 | I12: {=_xlfn.XLOOKUP(G12,Food_Menu!A:A,Food_Menu!D:D)} -> 200.38 | J12: D019 | K12: {=_xlfn.XLOOKUP(J12,Delivery_Partners!A:A,Delivery_Partners!B:B)} -> Delivery Partner 019 | L12: 3 | M12: Delivered | N12: Card | O12: 34 | P12: =I12*L12 -> 601.14 | Q12: =IF(O12="","Not Delivered",IF(O12<=30,"Fast",IF(O12<=60,"Normal","Slow"))) -> Normal
A13: O00012 | B13: 26/01/2025 | C13: C0822 | D13: {=_xlfn.XLOOKUP(C13,Customers!A:A,Customers!B:B)} -> Customer 0822 | E13: R059 | F13: {=_xlfn.XLOOKUP(E13,Restaurants!A:A,Restaurants!B:B)} -> Restaurant 059 | G13: F0073 | H13: {=_xlfn.XLOOKUP(G13,Food_Menu!A:A,Food_Menu!B:B)} -> Food Item 0073 | I13: {=_xlfn.XLOOKUP(G13,Food_Menu!A:A,Food_Menu!D:D)} -> 365.69 | J13: D114 | K13: {=_xlfn.XLOOKUP(J13,Delivery_Partners!A:A,Delivery_Partners!B:B)} -> Delivery Partner 114 | L13: 1 | M13: Delivered | N13: Cash | O13: 48 | P13: =I13*L13 -> 365.69 | Q13: =IF(O13="","Not Delivered",IF(O13<=30,"Fast",IF(O13<=60,"Normal","Slow"))) -> Normal
A14: O00013 | B14: 45781 | C14: C0359 | D14: {=_xlfn.XLOOKUP(C14,Customers!A:A,Customers!B:B)} -> Customer 0359 | E14: R018 | F14: {=_xlfn.XLOOKUP(E14,Restaurants!A:A,Restaurants!B:B)} -> Restaurant 018 | G14: F0189 | H14: {=_xlfn.XLOOKUP(G14,Food_Menu!A:A,Food_Menu!B:B)} -> Food Item 0189 | I14: {=_xlfn.XLOOKUP(G14,Food_Menu!A:A,Food_Menu!D:D)} -> 612.77 | J14: D170 | K14: {=_xlfn.XLOOKUP(J14,Delivery_Partners!A:A,Delivery_Partners!B:B)} -> Delivery Partner 170 | L14: 3 | M14: Delivered | N14: UPI | O14: 33 | P14: =I14*L14 -> 1838.31 | Q14: =IF(O14="","Not Delivered",IF(O14<=30,"Fast",IF(O14<=60,"Normal","Slow"))) -> Normal | S14: =SUM(P2:P8001) -> 4217825.2
A15: O00014 | B15: 45839 | C15: C0994 | D15: {=_xlfn.XLOOKUP(C15,Customers!A:A,Customers!B:B)} -> Customer 0994 | E15: R012 | F15: {=_xlfn.XLOOKUP(E15,Restaurants!A:A,Restaurants!B:B)} -> Restaurant 012 | G15: F0025 | H15: {=_xlfn.XLOOKUP(G15,Food_Menu!A:A,Food_Menu!B:B)} -> Food Item 0025 | J15: D092 | K15: {=_xlfn.XLOOKUP(J15,Delivery_Partners!A:A,Delivery_Partners!B:B)} -> Delivery Partner 092 | L15: 4 | M15: Cancelled | N15: UPI
A16: O00015 | B16: 15/12/2025 | C16: C0444 | D16: {=_xlfn.XLOOKUP(C16,Customers!A:A,Customers!B:B)} -> Customer 0444 | E16: R106 | F16: {=_xlfn.XLOOKUP(E16,Restaurants!A:A,Restaurants!B:B)} -> Restaurant 106 | G16: F0067 | H16: {=_xlfn.XLOOKUP(G16,Food_Menu!A:A,Food_Menu!B:B)} -> Food Item 0067 | I16: {=_xlfn.XLOOKUP(G16,Food_Menu!A:A,Food_Menu!D:D)} -> 575.59 | J16: D167 | K16: {=_xlfn.XLOOKUP(J16,Delivery_Partners!A:A,Delivery_Partners!B:B)} -> Delivery Partner 167 | L16: 1 | M16: Delivered | N16: UPI | O16: 62 | P16: =I16*L16 -> 575.59 | Q16: =IF(O16="","Not Delivered",IF(O16<=30,"Fast",IF(O16<=60,"Normal","Slow"))) -> Slow
A17: O00016 | B17: 45931 | C17: C0132 | D17: {=_xlfn.XLOOKUP(C17,Customers!A:A,Customers!B:B)} -> Customer 0132 | E17: R062 | F17: {=_xlfn.XLOOKUP(E17,Restaurants!A:A,Restaurants!B:B)} -> Restaurant 062 | G17: F0197 | H17: {=_xlfn.XLOOKUP(G17,Food_Menu!A:A,Food_Menu!B:B)} -> Food Item 0197 | I17: {=_xlfn.XLOOKUP(G17,Food_Menu!A:A,Food_Menu!D:D)} -> 628.28 | J17: D028 | K17: {=_xlfn.XLOOKUP(J17,Delivery_Partners!A:A,Delivery_Partners!B:B)} -> Delivery Partner 028 | L17: 1 | M17: Delivered | N17: Card | O17: 52 | P17: =I17*L17 -> 628.28 | Q17: =IF(O17="","Not Delivered",IF(O17<=30,"Fast",IF(O17<=60,"Normal","Slow"))) -> Normal
A18: O00017 | B18: 18/10/2025 | C18: C0115 | D18: {=_xlfn.XLOOKUP(C18,Customers!A:A,Customers!B:B)} -> Customer 0115 | E18: R086 | F18: {=_xlfn.XLOOKUP(E18,Restaurants!A:A,Restaurants!B:B)} -> Restaurant 086 | G18: F0030 | H18: {=_xlfn.XLOOKUP(G18,Food_Menu!A:A,Food_Menu!B:B)} -> Food Item 0030 | I18: {=_xlfn.XLOOKUP(G18,Food_Menu!A:A,Food_Menu!D:D)} -> 373.16 | J18: D176 | K18: {=_xlfn.XLOOKUP(J18,Delivery_Partners!A:A,Delivery_Partners!B:B)} -> Delivery Partner 176 | L18: 2 | M18: Delivered | N18: Cash | O18: 37 | P18: =I18*L18 -> 746.32 | Q18: =IF(O18="","Not Delivered",IF(O18<=30,"Fast",IF(O18<=60,"Normal","Slow"))) -> Normal | S18: =SUM(L2:L8001) -> 13368
A19: O00018 | B19: 45815 | C19: C0481 | D19: {=_xlfn.XLOOKUP(C19,Customers!A:A,Customers!B:B)} -> Customer 0481 | E19: R088 | F19: {=_xlfn.XLOOKUP(E19,Restaurants!A:A,Restaurants!B:B)} -> Restaurant 088 | G19: F0111 | H19: {=_xlfn.XLOOKUP(G19,Food_Menu!A:A,Food_Menu!B:B)} -> Food Item 0111 | I19: {=_xlfn.XLOOKUP(G19,Food_Menu!A:A,Food_Menu!D:D)} -> 237.65 | J19: D106 | K19: {=_xlfn.XLOOKUP(J19,Delivery_Partners!A:A,Delivery_Partners!B:B)} -> Delivery Partner 106 | L19: 3 | M19: Delivered | N19: UPI | O19: 23 | P19: =I19*L19 -> 712.95 | Q19: =IF(O19="","Not Delivered",IF(O19<=30,"Fast",IF(O19<=60,"Normal","Slow"))) -> Fast
A20: O00019 | B20: 45665 | C20: C0490 | D20: {=_xlfn.XLOOKUP(C20,Customers!A:A,Customers!B:B)} -> Customer 0490 | E20: R013 | F20: {=_xlfn.XLOOKUP(E20,Restaurants!A:A,Restaurants!B:B)} -> Restaurant 013 | G20: F0075 | H20: {=_xlfn.XLOOKUP(G20,Food_Menu!A:A,Food_Menu!B:B)} -> Food Item 0075 | I20: {=_xlfn.XLOOKUP(G20,Food_Menu!A:A,Food_Menu!D:D)} -> 613.26 | J20: D134 | K20: {=_xlfn.XLOOKUP(J20,Delivery_Partners!A:A,Delivery_Partners!B:B)} -> Delivery Partner 134 | L20: 1 | M20: Delivered | N20: UPI | O20: 15 | P20: =I20*L20 -> 613.26 | Q20: =IF(O20="","Not Delivered",IF(O20<=30,"Fast",IF(O20<=60,"Normal","Slow"))) -> Fast
A21: O00020 | B21: 24/10/2025 | C21: C0881 | D21: {=_xlfn.XLOOKUP(C21,Customers!A:A,Customers!B:B)} -> Customer 0881 | E21: R075 | F21: {=_xlfn.XLOOKUP(E21,Restaurants!A:A,Restaurants!B:B)} -> Restaurant 075 | G21: F0023 | H21: {=_xlfn.XLOOKUP(G21,Food_Menu!A:A,Food_Menu!B:B)} -> Food Item 0023 | I21: {=_xlfn.XLOOKUP(G21,Food_Menu!A:A,Food_Menu!D:D)} -> 276.1 | J21: D012 | K21: {=_xlfn.XLOOKUP(J21,Delivery_Partners!A:A,Delivery_Partners!B:B)} -> Delivery Partner 012 | L21: 1 | M21: Delivered | N21: Card | O21: 44 | P21: =I21*L21 -> 276.1 | Q21: =IF(O21="","Not Delivered",IF(O21<=30,"Fast",IF(O21<=60,"Normal","Slow"))) -> Normal
A22: O00021 | B22: 23/11/2025 | C22: C0575 | D22: {=_xlfn.XLOOKUP(C22,Customers!A:A,Customers!B:B)} -> Customer 0575 | E22: R104 | F22: {=_xlfn.XLOOKUP(E22,Restaurants!A:A,Restaurants!B:B)} -> Restaurant 104 | G22: F0052 | H22: {=_xlfn.XLOOKUP(G22,Food_Menu!A:A,Food_Menu!B:B)} -> Food Item 0052 | I22: {=_xlfn.XLOOKUP(G22,Food_Menu!A:A,Food_Menu!D:D)} -> 531.45 | J22: D109 | K22: {=_xlfn.XLOOKUP(J22,Delivery_Partners!A:A,Delivery_Partners!B:B)} -> Delivery Partner 109 | L22: 2 | M22: Delivered | N22: Card | O22: 50 | P22: =I22*L22 -> 1062.9 | Q22: =IF(O22="","Not Delivered",IF(O22<=30,"Fast",IF(O22<=60,"Normal","Slow"))) -> Normal
A23: O00022 | B23: 16/02/2025 | C23: C0197 | D23: {=_xlfn.XLOOKUP(C23,Customers!A:A,Customers!B:B)} -> Customer 0197 | E23: R054 | F23: {=_xlfn.XLOOKUP(E23,Restaurants!A:A,Restaurants!B:B)} -> Restaurant 054 | G23: F0118 | H23: {=_xlfn.XLOOKUP(G23,Food_Menu!A:A,Food_Menu!B:B)} -> Food Item 0118 | I23: {=_xlfn.XLOOKUP(G23,Food_Menu!A:A,Food_Menu!D:D)} -> 301.92 | J23: D069 | K23: {=_xlfn.XLOOKUP(J23,Delivery_Partners!A:A,Delivery_Partners!B:B)} -> Delivery Partner 069 | L23: 1 | M23: Delivered | N23: UPI | O23: 40 | P23: =I23*L23 -> 301.92 | Q23: =IF(O23="","Not Delivered",IF(O23<=30,"Fast",IF(O23<=60,"Normal","Slow"))) -> Normal
A24: O00023 | B24: 45839 | C24: C0256 | D24: {=_xlfn.XLOOKUP(C24,Customers!A:A,Customers!B:B)} -> Customer 0256 | E24: R104 | F24: {=_xlfn.XLOOKUP(E24,Restaurants!A:A,Restaurants!B:B)} -> Restaurant 104 | G24: F0139 | H24: {=_xlfn.XLOOKUP(G24,Food_Menu!A:A,Food_Menu!B:B)} -> Food Item 0139 | J24: D162 | K24: {=_xlfn.XLOOKUP(J24,Delivery_Partners!A:A,Delivery_Partners!B:B)} -> Delivery Partner 162 | L24: 2 | M24: Cancelled | N24: UPI
A25: O00024 | B25: 15/02/2025 | C25: C0680 | D25: {=_xlfn.XLOOKUP(C25,Customers!A:A,Customers!B:B)} -> Customer 0680 | E25: R114 | F25: {=_xlfn.XLOOKUP(E25,Restaurants!A:A,Restaurants!B:B)} -> Restaurant 114 | G25: F0149 | H25: {=_xlfn.XLOOKUP(G25,Food_Menu!A:A,Food_Menu!B:B)} -> Food Item 0149 | I25: {=_xlfn.XLOOKUP(G25,Food_Menu!A:A,Food_Menu!D:D)} -> 238.55 | J25: D143 | K25: {=_xlfn.XLOOKUP(J25,Delivery_Partners!A:A,Delivery_Partners!B:B)} -> Delivery Partner 143 | L25: 2 | M25: Delivered | N25: UPI | O25: 37 | P25: =I25*L25 -> 477.1 | Q25: =IF(O25="","Not Delivered",IF(O25<=30,"Fast",IF(O25<=60,"Normal","Slow"))) -> Normal
A26: O00025 | B26: 45847 | C26: C0402 | D26: {=_xlfn.XLOOKUP(C26,Customers!A:A,Customers!B:B)} -> Customer 0402 | E26: R066 | F26: {=_xlfn.XLOOKUP(E26,Restaurants!A:A,Restaurants!B:B)} -> Restaurant 066 | G26: F0029 | H26: {=_xlfn.XLOOKUP(G26,Food_Menu!A:A,Food_Menu!B:B)} -> Food Item 0029 | I26: {=_xlfn.XLOOKUP(G26,Food_Menu!A:A,Food_Menu!D:D)} -> 434.93 | J26: D156 | K26: {=_xlfn.XLOOKUP(J26,Delivery_Partners!A:A,Delivery_Partners!B:B)} -> Delivery Partner 156 | L26: 4 | M26: Delivered | N26: UPI | O26: 29 | P26: =I26*L26 -> 1739.72 | Q26: =IF(O26="","Not Delivered",IF(O26<=30,"Fast",IF(O26<=60,"Normal","Slow"))) -> Fast
A27: O00026 | B27: 27/07/2025 | C27: C0807 | D27: {=_xlfn.XLOOKUP(C27,Customers!A:A,Customers!B:B)} -> Customer 0807 | E27: R013 | F27: {=_xlfn.XLOOKUP(E27,Restaurants!A:A,Restaurants!B:B)} -> Restaurant 013 | G27: F0071 | H27: {=_xlfn.XLOOKUP(G27,Food_Menu!A:A,Food_Menu!B:B)} -> Food Item 0071 | J27: D161 | K27: {=_xlfn.XLOOKUP(J27,Delivery_Partners!A:A,Delivery_Partners!B:B)} -> Delivery Partner 161 | L27: 1 | M27: Cancelled | N27: UPI
A28: O00027 | B28: 31/01/2025 | C28: C1108 | D28: {=_xlfn.XLOOKUP(C28,Customers!A:A,Customers!B:B)} -> Customer 1108 | E28: R075 | F28: {=_xlfn.XLOOKUP(E28,Restaurants!A:A,Restaurants!B:B)} -> Restaurant 075 | G28: F0023 | H28: {=_xlfn.XLOOKUP(G28,Food_Menu!A:A,Food_Menu!B:B)} -> Food Item 0023 | I28: {=_xlfn.XLOOKUP(G28,Food_Menu!A:A,Food_Menu!D:D)} -> 276.1 | J28: D130 | K28: {=_xlfn.XLOOKUP(J28,Delivery_Partners!A:A,Delivery_Partners!B:B)} -> Delivery Partner 130 | L28: 3 | M28: Delivered | N28: Card | O28: 58 | P28: =I28*L28 -> 828.3 | Q28: =IF(O28="","Not Delivered",IF(O28<=30,"Fast",IF(O28<=60,"Normal","Slow"))) -> Normal
A29: O00028 | B29: 27/03/2025 | C29: C0426 | D29: {=_xlfn.XLOOKUP(C29,Customers!A:A,Customers!B:B)} -> Customer 0426 | E29: R106 | F29: {=_xlfn.XLOOKUP(E29,Restaurants!A:A,Restaurants!B:B)} -> Restaurant 106 | G29: F0003 | H29: {=_xlfn.XLOOKUP(G29,Food_Menu!A:A,Food_Menu!B:B)} -> Food Item 0003 | I29: {=_xlfn.XLOOKUP(G29,Food_Menu!A:A,Food_Menu!D:D)} -> 349.88 | J29: D045 | K29: {=_xlfn.XLOOKUP(J29,Delivery_Partners!A:A,Delivery_Partners!B:B)} -> Delivery Partner 045 | L29: 2 | M29: Delivered | N29: Cash | O29: 44 | P29: =I29*L29 -> 699.76 | Q29: =IF(O29="","Not Delivered",IF(O29<=30,"Fast",IF(O29<=60,"Normal","Slow"))) -> Normal
A30: O00029 | B30: 16/07/2025 | C30: C0663 | D30: {=_xlfn.XLOOKUP(C30,Customers!A:A,Customers!B:B)} -> Customer 0663 | E30: R070 | F30: {=_xlfn.XLOOKUP(E30,Restaurants!A:A,Restaurants!B:B)} -> Restaurant 070 | G30: F0086 | H30: {=_xlfn.XLOOKUP(G30,Food_Menu!A:A,Food_Menu!B:B)} -> Food Item 0086 | I30: {=_xlfn.XLOOKUP(G30,Food_Menu!A:A,Food_Menu!D:D)} -> 475.88 | J30: D051 | K30: {=_xlfn.XLOOKUP(J30,Delivery_Partners!A:A,Delivery_Partners!B:B)} -> Delivery Partner 051 | L30: 3 | M30: Delivered | N30: Card | O30: 42 | P30: =I30*L30 -> 1427.64 | Q30: =IF(O30="","Not Delivered",IF(O30<=30,"Fast",IF(O30<=60,"Normal","Slow"))) -> Normal
A31: O00030 | B31: 24/09/2025 | C31: C0999 | D31: {=_xlfn.XLOOKUP(C31,Customers!A:A,Customers!B:B)} -> Customer 0999 | E31: R097 | F31: {=_xlfn.XLOOKUP(E31,Restaurants!A:A,Restaurants!B:B)} -> Restaurant 097 | G31: F0137 | H31: {=_xlfn.XLOOKUP(G31,Food_Menu!A:A,Food_Menu!B:B)} -> Food Item 0137 | I31: {=_xlfn.XLOOKUP(G31,Food_Menu!A:A,Food_Menu!D:D)} -> 200.4 | J31: D155 | K31: {=_xlfn.XLOOKUP(J31,Delivery_Partners!A:A,Delivery_Partners!B:B)} -> Delivery Partner 155 | L31: 1 | M31: Delivered | N31: UPI | O31: 34 | P31: =I31*L31 -> 200.4 | Q31: =IF(O31="","Not Delivered",IF(O31<=30,"Fast",IF(O31<=60,"Normal","Slow"))) -> Normal
A32: O00031 | B32: 45813 | C32: C0253 | D32: {=_xlfn.XLOOKUP(C32,Customers!A:A,Customers!B:B)} -> Customer 0253 | E32: R065 | F32: {=_xlfn.XLOOKUP(E32,Restaurants!A:A,Restaurants!B:B)} -> Restaurant 065 | G32: F0082 | H32: {=_xlfn.XLOOKUP(G32,Food_Menu!A:A,Food_Menu!B:B)} -> Food Item 0082 | J32: D109 | K32: {=_xlfn.XLOOKUP(J32,Delivery_Partners!A:A,Delivery_Partners!B:B)} -> Delivery Partner 109 | L32: 2 | M32: Failed | N32: UPI
A33: O00032 | B33: 13/12/2025 | C33: C0613 | D33: {=_xlfn.XLOOKUP(C33,Customers!A:A,Customers!B:B)} -> Customer 0613 | E33: R051 | F33: {=_xlfn.XLOOKUP(E33,Restaurants!A:A,Restaurants!B:B)} -> Restaurant 051 | G33: F0009 | H33: {=_xlfn.XLOOKUP(G33,Food_Menu!A:A,Food_Menu!B:B)} -> Food Item 0009 | I33: {=_xlfn.XLOOKUP(G33,Food_Menu!A:A,Food_Menu!D:D)} -> 168.03 | J33: D161 | K33: {=_xlfn.XLOOKUP(J33,Delivery_Partners!A:A,Delivery_Partners!B:B)} -> Delivery Partner 161 | L33: 3 | M33: Delivered | N33: Cash | O33: 26 | P33: =I33*L33 -> 504.09 | Q33: =IF(O33="","Not Delivered",IF(O33<=30,"Fast",IF(O33<=60,"Normal","Slow"))) -> Fast
A34: O00033 | B34: 29/12/2025 | C34: C0367 | D34: {=_xlfn.XLOOKUP(C34,Customers!A:A,Customers!B:B)} -> Customer 0367 | E34: R114 | F34: {=_xlfn.XLOOKUP(E34,Restaurants!A:A,Restaurants!B:B)} -> Restaurant 114 | G34: F0049 | H34: {=_xlfn.XLOOKUP(G34,Food_Menu!A:A,Food_Menu!B:B)} -> Food Item 0049 | I34: {=_xlfn.XLOOKUP(G34,Food_Menu!A:A,Food_Menu!D:D)} -> 504.81 | J34: D144 | K34: {=_xlfn.XLOOKUP(J34,Delivery_Partners!A:A,Delivery_Partners!B:B)} -> Delivery Partner 144 | L34: 2 | M34: Delivered | N34: Card | O34: 42 | P34: =I34*L34 -> 1009.62 | Q34: =IF(O34="","Not Delivered",IF(O34<=30,"Fast",IF(O34<=60,"Normal","Slow"))) -> Normal
A35: O00034 | B35: 45848 | C35: C0753 | D35: {=_xlfn.XLOOKUP(C35,Customers!A:A,Customers!B:B)} -> Customer 0753 | E35: R019 | F35: {=_xlfn.XLOOKUP(E35,Restaurants!A:A,Restaurants!B:B)} -> Restaurant 019 | G35: F0096 | H35: {=_xlfn.XLOOKUP(G35,Food_Menu!A:A,Food_Menu!B:B)} -> Food Item 0096 | J35: D110 | K35: {=_xlfn.XLOOKUP(J35,Delivery_Partners!A:A,Delivery_Partners!B:B)} -> Delivery Partner 110 | L35: 1 | M35: Cancelled | N35: Cash
A36: O00035 | B36: 15/06/2025 | C36: C0892 | D36: {=_xlfn.XLOOKUP(C36,Customers!A:A,Customers!B:B)} -> Customer 0892 | E36: R054 | F36: {=_xlfn.XLOOKUP(E36,Restaurants!A:A,Restaurants!B:B)} -> Restaurant 054 | G36: F0079 | H36: {=_xlfn.XLOOKUP(G36,Food_Menu!A:A,Food_Menu!B:B)} -> Food Item 0079 | I36: {=_xlfn.XLOOKUP(G36,Food_Menu!A:A,Food_Menu!D:D)} -> 193.41 | J36: D028 | K36: {=_xlfn.XLOOKUP(J36,Delivery_Partners!A:A,Delivery_Partners!B:B)} -> Delivery Partner 028 | L36: 1 | M36: Delivered | N36: UPI | O36: 25 | P36: =I36*L36 -> 193.41 | Q36: =IF(O36="","Not Delivered",IF(O36<=30,"Fast",IF(O36<=60,"Normal","Slow"))) -> Fast
A37: O00036 | B37: 17/11/2025 | C37: C0170 | D37: {=_xlfn.XLOOKUP(C37,Customers!A:A,Customers!B:B)} -> Customer 0170 | E37: R019 | F37: {=_xlfn.XLOOKUP(E37,Restaurants!A:A,Restaurants!B:B)} -> Restaurant 019 | G37: F0182 | H37: {=_xlfn.XLOOKUP(G37,Food_Menu!A:A,Food_Menu!B:B)} -> Food Item 0182 | I37: {=_xlfn.XLOOKUP(G37,Food_Menu!A:A,Food_Menu!D:D)} -> 512.27 | J37: D177 | K37: {=_xlfn.XLOOKUP(J37,Delivery_Partners!A:A,Delivery_Partners!B:B)} -> Delivery Partner 177 | L37: 1 | M37: Delivered | N37: UPI | O37: 45 | P37: =I37*L37 -> 512.27 | Q37: =IF(O37="","Not Delivered",IF(O37<=30,"Fast",IF(O37<=60,"Normal","Slow"))) -> Normal
A38: O00037 | B38: 23/09/2025 | C38: C0225 | D38: {=_xlfn.XLOOKUP(C38,Customers!A:A,Customers!B:B)} -> Customer 0225 | E38: R079 | F38: {=_xlfn.XLOOKUP(E38,Restaurants!A:A,Restaurants!B:B)} -> Restaurant 079 | G38: F0132 | H38: {=_xlfn.XLOOKUP(G38,Food_Menu!A:A,Food_Menu!B:B)} -> Food Item 0132 | I38: {=_xlfn.XLOOKUP(G38,Food_Menu!A:A,Food_Menu!D:D)} -> 597.76 | J38: D044 | K38: {=_xlfn.XLOOKUP(J38,Delivery_Partners!A:A,Delivery_Partners!B:B)} -> Delivery Partner 044 | L38: 1 | M38: Delivered | N38: Wallet | O38: 15 | P38: =I38*L38 -> 597.76 | Q38: =IF(O38="","Not Delivered",IF(O38<=30,"Fast",IF(O38<=60,"Normal","Slow"))) -> Fast
A39: O00038 | B39: 45907 | C39: C0028 | D39: {=_xlfn.XLOOKUP(C39,Customers!A:A,Customers!B:B)} -> Customer 0028 | E39: R111 | F39: {=_xlfn.XLOOKUP(E39,Restaurants!A:A,Restaurants!B:B)} -> Restaurant 111 | G39: F0220 | H39: {=_xlfn.XLOOKUP(G39,Food_Menu!A:A,Food_Menu!B:B)} -> Food Item 0220 | I39: {=_xlfn.XLOOKUP(G39,Food_Menu!A:A,Food_Menu!D:D)} -> 194.15 | J39: D045 | K39: {=_xlfn.XLOOKUP(J39,Delivery_Partners!A:A,Delivery_Partners!B:B)} -> Delivery Partner 045 | L39: 2 | M39: Delivered | N39: UPI | O39: 28 | P39: =I39*L39 -> 388.3 | Q39: =IF(O39="","Not Delivered",IF(O39<=30,"Fast",IF(O39<=60,"Normal","Slow"))) -> Fast
A40: O00039 | B40: 45967 | C40: C0015 | D40: {=_xlfn.XLOOKUP(C40,Customers!A:A,Customers!B:B)} -> Customer 0015 | E40: R120 | F40: {=_xlfn.XLOOKUP(E40,Restaurants!A:A,Restaurants!B:B)} -> Restaurant 120 | G40: F0039 | H40: {=_xlfn.XLOOKUP(G40,Food_Menu!A:A,Food_Menu!B:B)} -> Food Item 0039 | I40: {=_xlfn.XLOOKUP(G40,Food_Menu!A:A,Food_Menu!D:D)} -> 557.2 | J40: D027 | K40: {=_xlfn.XLOOKUP(J40,Delivery_Partners!A:A,Delivery_Partners!B:B)} -> Delivery Partner 027 | L40: 4 | M40: Delivered | N40: UPI | O40: 42 | P40: =I40*L40 -> 2228.8 | Q40: =IF(O40="","Not Delivered",IF(O40<=30,"Fast",IF(O40<=60,"Normal","Slow"))) -> Normal
A41: O00040 | B41: 31/10/2025 | C41: C0061 | D41: {=_xlfn.XLOOKUP(C41,Customers!A:A,Customers!B:B)} -> Customer 0061 | E41: R029 | F41: {=_xlfn.XLOOKUP(E41,Restaurants!A:A,Restaurants!B:B)} -> Restaurant 029 | G41: F0082 | H41: {=_xlfn.XLOOKUP(G41,Food_Menu!A:A,Food_Menu!B:B)} -> Food Item 0082 | I41: {=_xlfn.XLOOKUP(G41,Food_Menu!A:A,Food_Menu!D:D)} -> 266.68 | J41: D013 | K41: {=_xlfn.XLOOKUP(J41,Delivery_Partners!A:A,Delivery_Partners!B:B)} -> Delivery Partner 013 | L41: 2 | M41: Delivered | N41: Card | O41: 50 | P41: =I41*L41 -> 533.36 | Q41: =IF(O41="","Not Delivered",IF(O41<=30,"Fast",IF(O41<=60,"Normal","Slow"))) -> Normal
A42: O00041 | B42: 23/07/2025 | C42: C0849 | D42: {=_xlfn.XLOOKUP(C42,Customers!A:A,Customers!B:B)} -> Customer 0849 | E42: R088 | F42: {=_xlfn.XLOOKUP(E42,Restaurants!A:A,Restaurants!B:B)} -> Restaurant 088 | G42: F0020 | H42: {=_xlfn.XLOOKUP(G42,Food_Menu!A:A,Food_Menu!B:B)} -> Food Item 0020 | I42: {=_xlfn.XLOOKUP(G42,Food_Menu!A:A,Food_Menu!D:D)} -> 565.62 | J42: D068 | K42: {=_xlfn.XLOOKUP(J42,Delivery_Partners!A:A,Delivery_Partners!B:B)} -> Delivery Partner 068 | L42: 1 | M42: Delivered | N42: Card | O42: 41 | P42: =I42*L42 -> 565.62 | Q42: =IF(O42="","Not Delivered",IF(O42<=30,"Fast",IF(O42<=60,"Normal","Slow"))) -> Normal
A43: O00042 | B43: 45872 | C43: C1085 | D43: {=_xlfn.XLOOKUP(C43,Customers!A:A,Customers!B:B)} -> Customer 1085 | E43: R105 | F43: {=_xlfn.XLOOKUP(E43,Restaurants!A:A,Restaurants!B:B)} -> Restaurant 105 | G43: F0005 | H43: {=_xlfn.XLOOKUP(G43,Food_Menu!A:A,Food_Menu!B:B)} -> Food Item 0005 | I43: {=_xlfn.XLOOKUP(G43,Food_Menu!A:A,Food_Menu!D:D)} -> 481.92 | J43: D152 | K43: {=_xlfn.XLOOKUP(J43,Delivery_Partners!A:A,Delivery_Partners!B:B)} -> Delivery Partner 152 | L43: 1 | M43: Delivered | N43: UPI | O43: 27 | P43: =I43*L43 -> 481.92 | Q43: =IF(O43="","Not Delivered",IF(O43<=30,"Fast",IF(O43<=60,"Normal","Slow"))) -> Fast
A44: O00043 | B44: 31/12/2025 | C44: C0492 | D44: {=_xlfn.XLOOKUP(C44,Customers!A:A,Customers!B:B)} -> Customer 0492 | E44: R101 | F44: {=_xlfn.XLOOKUP(E44,Restaurants!A:A,Restaurants!B:B)} -> Restaurant 101 | G44: F0204 | H44: {=_xlfn.XLOOKUP(G44,Food_Menu!A:A,Food_Menu!B:B)} -> Food Item 0204 | I44: {=_xlfn.XLOOKUP(G44,Food_Menu!A:A,Food_Menu!D:D)} -> 410.12 | J44: D156 | K44: {=_xlfn.XLOOKUP(J44,Delivery_Partners!A:A,Delivery_Partners!B:B)} -> Delivery Partner 156 | L44: 1 | M44: Delivered | N44: Card | O44: 34 | P44: =I44*L44 -> 410.12 | Q44: =IF(O44="","Not Delivered",IF(O44<=30,"Fast",IF(O44<=60,"Normal","Slow"))) -> Normal
A45: O00044 | B45: 25/01/2025 | C45: C1060 | D45: {=_xlfn.XLOOKUP(C45,Customers!A:A,Customers!B:B)} -> Customer 1060 | E45: R061 | F45: {=_xlfn.XLOOKUP(E45,Restaurants!A:A,Restaurants!B:B)} -> Restaurant 061 | G45: F0109 | H45: {=_xlfn.XLOOKUP(G45,Food_Menu!A:A,Food_Menu!B:B)} -> Food Item 0109 | I45: {=_xlfn.XLOOKUP(G45,Food_Menu!A:A,Food_Menu!D:D)} -> 538.59 | J45: D089 | K45: {=_xlfn.XLOOKUP(J45,Delivery_Partners!A:A,Delivery_Partners!B:B)} -> Delivery Partner 089 | L45: 1 | M45: Delivered | N45: UPI | O45: 38 | P45: =I45*L45 -> 538.59 | Q45: =IF(O45="","Not Delivered",IF(O45<=30,"Fast",IF(O45<=60,"Normal","Slow"))) -> Normal
A46: O00045 | B46: 45970 | C46: C0876 | D46: {=_xlfn.XLOOKUP(C46,Customers!A:A,Customers!B:B)} -> Customer 0876 | E46: R021 | F46: {=_xlfn.XLOOKUP(E46,Restaurants!A:A,Restaurants!B:B)} -> Restaurant 021 | G46: F0146 | H46: {=_xlfn.XLOOKUP(G46,Food_Menu!A:A,Food_Menu!B:B)} -> Food Item 0146 | I46: {=_xlfn.XLOOKUP(G46,Food_Menu!A:A,Food_Menu!D:D)} -> 580.64 | J46: D057 | K46: {=_xlfn.XLOOKUP(J46,Delivery_Partners!A:A,Delivery_Partners!B:B)} -> Delivery Partner 057 | L46: 3 | M46: Delivered | N46: Cash | O46: 54 | P46: =I46*L46 -> 1741.92 | Q46: =IF(O46="","Not Delivered",IF(O46<=30,"Fast",IF(O46<=60,"Normal","Slow"))) -> Normal
A47: O00046 | B47: 28/08/2025 | C47: C0970 | D47: {=_xlfn.XLOOKUP(C47,Customers!A:A,Customers!B:B)} -> Customer 0970 | E47: R056 | F47: {=_xlfn.XLOOKUP(E47,Restaurants!A:A,Restaurants!B:B)} -> Restaurant 056 | G47: F0061 | H47: {=_xlfn.XLOOKUP(G47,Food_Menu!A:A,Food_Menu!B:B)} -> Food Item 0061 | I47: {=_xlfn.XLOOKUP(G47,Food_Menu!A:A,Food_Menu!D:D)} -> 538.21 | J47: D063 | K47: {=_xlfn.XLOOKUP(J47,Delivery_Partners!A:A,Delivery_Partners!B:B)} -> Delivery Partner 063 | L47: 1 | M47: Delivered | N47: Cash | O47: 46 | P47: =I47*L47 -> 538.21 | Q47: =IF(O47="","Not Delivered",IF(O47<=30,"Fast",IF(O47<=60,"Normal","Slow"))) -> Normal
A48: O00047 | B48: 45696 | C48: C0888 | D48: {=_xlfn.XLOOKUP(C48,Customers!A:A,Customers!B:B)} -> Customer 0888 | E48: R094 | F48: {=_xlfn.XLOOKUP(E48,Restaurants!A:A,Restaurants!B:B)} -> Restaurant 094 | G48: F0012 | H48: {=_xlfn.XLOOKUP(G48,Food_Menu!A:A,Food_Menu!B:B)} -> Food Item 0012 | I48: {=_xlfn.XLOOKUP(G48,Food_Menu!A:A,Food_Menu!D:D)} -> 390.14 | J48: D166 | K48: {=_xlfn.XLOOKUP(J48,Delivery_Partners!A:A,Delivery_Partners!B:B)} -> Delivery Partner 166 | L48: 1 | M48: Delivered | N48: Card | O48: 46 | P48: =I48*L48 -> 390.14 | Q48: =IF(O48="","Not Delivered",IF(O48<=30,"Fast",IF(O48<=60,"Normal","Slow"))) -> Normal
A49: O00048 | B49: 19/01/2025 | C49: C0240 | D49: {=_xlfn.XLOOKUP(C49,Customers!A:A,Customers!B:B)} -> Customer 0240 | E49: R075 | F49: {=_xlfn.XLOOKUP(E49,Restaurants!A:A,Restaurants!B:B)} -> Restaurant 075 | G49: F0197 | H49: {=_xlfn.XLOOKUP(G49,Food_Menu!A:A,Food_Menu!B:B)} -> Food Item 0197 | I49: {=_xlfn.XLOOKUP(G49,Food_Menu!A:A,Food_Menu!D:D)} -> 628.28 | J49: D010 | K49: {=_xlfn.XLOOKUP(J49,Delivery_Partners!A:A,Delivery_Partners!B:B)} -> Delivery Partner 010 | L49: 2 | M49: Delivered | N49: UPI | O49: 36 | P49: =I49*L49 -> 1256.56 | Q49: =IF(O49="","Not Delivered",IF(O49<=30,"Fast",IF(O49<=60,"Normal","Slow"))) -> Normal
A50: O00049 | B50: 29/06/2025 | C50: C0629 | D50: {=_xlfn.XLOOKUP(C50,Customers!A:A,Customers!B:B)} -> Customer 0629 | E50: R047 | F50: {=_xlfn.XLOOKUP(E50,Restaurants!A:A,Restaurants!B:B)} -> Restaurant 047 | G50: F0145 | H50: {=_xlfn.XLOOKUP(G50,Food_Menu!A:A,Food_Menu!B:B)} -> Food Item 0145 | I50: {=_xlfn.XLOOKUP(G50,Food_Menu!A:A,Food_Menu!D:D)} -> 530.68 | J50: D011 | K50: {=_xlfn.XLOOKUP(J50,Delivery_Partners!A:A,Delivery_Partners!B:B)} -> Delivery Partner 011 | L50: 1 | M50: Delivered | N50: UPI | O50: 22 | P50: =I50*L50 -> 530.68 | Q50: =IF(O50="","Not Delivered",IF(O50<=30,"Fast",IF(O50<=60,"Normal","Slow"))) -> Fast
A51: O00050 | B51: 22/11/2025 | C51: C0631 | D51: {=_xlfn.XLOOKUP(C51,Customers!A:A,Customers!B:B)} -> Customer 0631 | E51: R026 | F51: {=_xlfn.XLOOKUP(E51,Restaurants!A:A,Restaurants!B:B)} -> Restaurant 026 | G51: F0157 | H51: {=_xlfn.XLOOKUP(G51,Food_Menu!A:A,Food_Menu!B:B)} -> Food Item 0157 | I51: {=_xlfn.XLOOKUP(G51,Food_Menu!A:A,Food_Menu!D:D)} -> 278.37 | J51: D012 | K51: {=_xlfn.XLOOKUP(J51,Delivery_Partners!A:A,Delivery_Partners!B:B)} -> Delivery Partner 012 | L51: 1 | M51: Delivered | N51: Cash | O51: 18 | P51: =I51*L51 -> 278.37 | Q51: =IF(O51="","Not Delivered",IF(O51<=30,"Fast",IF(O51<=60,"Normal","Slow"))) -> Fast
A52: O00051 | B52: 29/03/2025 | C52: C0770 | D52: {=_xlfn.XLOOKUP(C52,Customers!A:A,Customers!B:B)} -> Customer 0770 | E52: R079 | F52: {=_xlfn.XLOOKUP(E52,Restaurants!A:A,Restaurants!B:B)} -> Restaurant 079 | G52: F0118 | H52: {=_xlfn.XLOOKUP(G52,Food_Menu!A:A,Food_Menu!B:B)} -> Food Item 0118 | I52: {=_xlfn.XLOOKUP(G52,Food_Menu!A:A,Food_Menu!D:D)} -> 301.92 | J52: D160 | K52: {=_xlfn.XLOOKUP(J52,Delivery_Partners!A:A,Delivery_Partners!B:B)} -> Delivery Partner 160 | L52: 1 | M52: Delivered | N52: UPI | O52: 31 | P52: =I52*L52 -> 301.92 | Q52: =IF(O52="","Not Delivered",IF(O52<=30,"Fast",IF(O52<=60,"Normal","Slow"))) -> Normal
A53: O00052 | B53: 45939 | C53: C0956 | D53: {=_xlfn.XLOOKUP(C53,Customers!A:A,Customers!B:B)} -> Customer 0956 | E53: R052 | F53: {=_xlfn.XLOOKUP(E53,Restaurants!A:A,Restaurants!B:B)} -> Restaurant 052 | G53: F0089 | H53: {=_xlfn.XLOOKUP(G53,Food_Menu!A:A,Food_Menu!B:B)} -> Food Item 0089 | I53: {=_xlfn.XLOOKUP(G53,Food_Menu!A:A,Food_Menu!D:D)} -> 262.73 | J53: D017 | K53: {=_xlfn.XLOOKUP(J53,Delivery_Partners!A:A,Delivery_Partners!B:B)} -> Delivery Partner 017 | L53: 1 | M53: Delivered | N53: UPI | O53: 43 | P53: =I53*L53 -> 262.73 | Q53: =IF(O53="","Not Delivered",IF(O53<=30,"Fast",IF(O53<=60,"Normal","Slow"))) -> Normal
A54: O00053 | B54: 45941 | C54: C0136 | D54: {=_xlfn.XLOOKUP(C54,Customers!A:A,Customers!B:B)} -> Customer 0136 | E54: R057 | F54: {=_xlfn.XLOOKUP(E54,Restaurants!A:A,Restaurants!B:B)} -> Restaurant 057 | G54: F0093 | H54: {=_xlfn.XLOOKUP(G54,Food_Menu!A:A,Food_Menu!B:B)} -> Food Item 0093 | I54: {=_xlfn.XLOOKUP(G54,Food_Menu!A:A,Food_Menu!D:D)} -> 337.02 | J54: D170 | K54: {=_xlfn.XLOOKUP(J54,Delivery_Partners!A:A,Delivery_Partners!B:B)} -> Delivery Partner 170 | L54: 2 | M54: Delivered | N54: Wallet | O54: 29 | P54: =I54*L54 -> 674.04 | Q54: =IF(O54="","Not Delivered",IF(O54<=30,"Fast",IF(O54<=60,"Normal","Slow"))) -> Fast
A55: O00054 | B55: 14/12/2025 | C55: C0810 | D55: {=_xlfn.XLOOKUP(C55,Customers!A:A,Customers!B:B)} -> Customer 0810 | E55: R113 | F55: {=_xlfn.XLOOKUP(E55,Restaurants!A:A,Restaurants!B:B)} -> Restaurant 113 | G55: F0168 | H55: {=_xlfn.XLOOKUP(G55,Food_Menu!A:A,Food_Menu!B:B)} -> Food Item 0168 | I55: {=_xlfn.XLOOKUP(G55,Food_Menu!A:A,Food_Menu!D:D)} -> 107.01 | J55: D034 | K55: {=_xlfn.XLOOKUP(J55,Delivery_Partners!A:A,Delivery_Partners!B:B)} -> Delivery Partner 034 | L55: 1 | M55: Delivered | N55: Cash | O55: 42 | P55: =I55*L55 -> 107.01 | Q55: =IF(O55="","Not Delivered",IF(O55<=30,"Fast",IF(O55<=60,"Normal","Slow"))) -> Normal
A56: O00055 | B56: 45876 | C56: C1000 | D56: {=_xlfn.XLOOKUP(C56,Customers!A:A,Customers!B:B)} -> Customer 1000 | E56: R002 | F56: {=_xlfn.XLOOKUP(E56,Restaurants!A:A,Restaurants!B:B)} -> Restaurant 002 | G56: F0050 | H56: {=_xlfn.XLOOKUP(G56,Food_Menu!A:A,Food_Menu!B:B)} -> Food Item 0050 | J56: D099 | K56: {=_xlfn.XLOOKUP(J56,Delivery_Partners!A:A,Delivery_Partners!B:B)} -> Delivery Partner 099 | L56: 2 | M56: Failed | N56: Wallet
A57: O00056 | B57: 25/04/2025 | C57: C0139 | D57: {=_xlfn.XLOOKUP(C57,Customers!A:A,Customers!B:B)} -> Customer 0139 | E57: R029 | F57: {=_xlfn.XLOOKUP(E57,Restaurants!A:A,Restaurants!B:B)} -> Restaurant 029 | G57: F0076 | H57: {=_xlfn.XLOOKUP(G57,Food_Menu!A:A,Food_Menu!B:B)} -> Food Item 0076 | I57: {=_xlfn.XLOOKUP(G57,Food_Menu!A:A,Food_Menu!D:D)} -> 82.28 | J57: D175 | K57: {=_xlfn.XLOOKUP(J57,Delivery_Partners!A:A,Delivery_Partners!B:B)} -> Delivery Partner 175 | L57: 1 | M57: Delivered | N57: UPI | O57: 27 | P57: =I57*L57 -> 82.28 | Q57: =IF(O57="","Not Delivered",IF(O57<=30,"Fast",IF(O57<=60,"Normal","Slow"))) -> Fast
A58: O00057 | B58: 13/09/2025 | C58: C0498 | D58: {=_xlfn.XLOOKUP(C58,Customers!A:A,Customers!B:B)} -> Customer 0498 | E58: R111 | F58: {=_xlfn.XLOOKUP(E58,Restaurants!A:A,Restaurants!B:B)} -> Restaurant 111 | G58: F0068 | H58: {=_xlfn.XLOOKUP(G58,Food_Menu!A:A,Food_Menu!B:B)} -> Food Item 0068 | I58: {=_xlfn.XLOOKUP(G58,Food_Menu!A:A,Food_Menu!D:D)} -> 583.22 | J58: D021 | K58: {=_xlfn.XLOOKUP(J58,Delivery_Partners!A:A,Delivery_Partners!B:B)} -> Delivery Partner 021 | L58: 1 | M58: Delivered | N58: UPI | O58: 52 | P58: =I58*L58 -> 583.22 | Q58: =IF(O58="","Not Delivered",IF(O58<=30,"Fast",IF(O58<=60,"Normal","Slow"))) -> Normal
A59: O00058 | B59: 27/06/2025 | C59: C1075 | D59: {=_xlfn.XLOOKUP(C59,Customers!A:A,Customers!B:B)} -> Customer 1075 | E59: R111 | F59: {=_xlfn.XLOOKUP(E59,Restaurants!A:A,Restaurants!B:B)} -> Restaurant 111 | G59: F0115 | H59: {=_xlfn.XLOOKUP(G59,Food_Menu!A:A,Food_Menu!B:B)} -> Food Item 0115 | I59: {=_xlfn.XLOOKUP(G59,Food_Menu!A:A,Food_Menu!D:D)} -> 109.53 | J59: D051 | K59: {=_xlfn.XLOOKUP(J59,Delivery_Partners!A:A,Delivery_Partners!B:B)} -> Delivery Partner 051 | L59: 2 | M59: Delivered | N59: UPI | O59: 44 | P59: =I59*L59 -> 219.06 | Q59: =IF(O59="","Not Delivered",IF(O59<=30,"Fast",IF(O59<=60,"Normal","Slow"))) -> Normal
A60: O00059 | B60: 17/08/2025 | C60: C0030 | D60: {=_xlfn.XLOOKUP(C60,Customers!A:A,Customers!B:B)} -> Customer 0030 | E60: R037 | F60: {=_xlfn.XLOOKUP(E60,Restaurants!A:A,Restaurants!B:B)} -> Restaurant 037 | G60: F0213 | H60: {=_xlfn.XLOOKUP(G60,Food_Menu!A:A,Food_Menu!B:B)} -> Food Item 0213 | I60: {=_xlfn.XLOOKUP(G60,Food_Menu!A:A,Food_Menu!D:D)} -> 568.2 | J60: D131 | K60: {=_xlfn.XLOOKUP(J60,Delivery_Partners!A:A,Delivery_Partners!B:B)} -> Delivery Partner 131 | L60: 1 | M60: Delivered | N60: Card | O60: 31 | P60: =I60*L60 -> 568.2 | Q60: =IF(O60="","Not Delivered",IF(O60<=30,"Fast",IF(O60<=60,"Normal","Slow"))) -> Normal
A61: O00060 | B61: 28/09/2025 | C61: C0193 | D61: {=_xlfn.XLOOKUP(C61,Customers!A:A,Customers!B:B)} -> Customer 0193 | E61: R120 | F61: {=_xlfn.XLOOKUP(E61,Restaurants!A:A,Restaurants!B:B)} -> Restaurant 120 | G61: F0204 | H61: {=_xlfn.XLOOKUP(G61,Food_Menu!A:A,Food_Menu!B:B)} -> Food Item 0204 | I61: {=_xlfn.XLOOKUP(G61,Food_Menu!A:A,Food_Menu!D:D)} -> 410.12 | J61: D148 | K61: {=_xlfn.XLOOKUP(J61,Delivery_Partners!A:A,Delivery_Partners!B:B)} -> Delivery Partner 148 | L61: 1 | M61: Delivered | N61: Cash | O61: 25 | P61: =I61*L61 -> 410.12 | Q61: =IF(O61="","Not Delivered",IF(O61<=30,"Fast",IF(O61<=60,"Normal","Slow"))) -> Fast
A62: O00061 | B62: 17/09/2025 | C62: C0965 | D62: {=_xlfn.XLOOKUP(C62,Customers!A:A,Customers!B:B)} -> Customer 0965 | E62: R026 | F62: {=_xlfn.XLOOKUP(E62,Restaurants!A:A,Restaurants!B:B)} -> Restaurant 026 | G62: F0120 | H62: {=_xlfn.XLOOKUP(G62,Food_Menu!A:A,Food_Menu!B:B)} -> Food Item 0120 | I62: {=_xlfn.XLOOKUP(G62,Food_Menu!A:A,Food_Menu!D:D)} -> 569.73 | J62: D164 | K62: {=_xlfn.XLOOKUP(J62,Delivery_Partners!A:A,Delivery_Partners!B:B)} -> Delivery Partner 164 | L62: 1 | M62: Delivered | N62: UPI | O62: 46 | P62: =I62*L62 -> 569.73 | Q62: =IF(O62="","Not Delivered",IF(O62<=30,"Fast",IF(O62<=60,"Normal","Slow"))) -> Normal
A63: O00062 | B63: 30/03/2025 | C63: C0207 | D63: {=_xlfn.XLOOKUP(C63,Customers!A:A,Customers!B:B)} -> Customer 0207 | E63: R007 | F63: {=_xlfn.XLOOKUP(E63,Restaurants!A:A,Restaurants!B:B)} -> Restaurant 007 | G63: F0045 | H63: {=_xlfn.XLOOKUP(G63,Food_Menu!A:A,Food_Menu!B:B)} -> Food Item 0045 | I63: {=_xlfn.XLOOKUP(G63,Food_Menu!A:A,Food_Menu!D:D)} -> 263.72 | J63: D004 | K63: {=_xlfn.XLOOKUP(J63,Delivery_Partners!A:A,Delivery_Partners!B:B)} -> Delivery Partner 004 | L63: 1 | M63: Delivered | N63: UPI | O63: 46 | P63: =I63*L63 -> 263.72 | Q63: =IF(O63="","Not Delivered",IF(O63<=30,"Fast",IF(O63<=60,"Normal","Slow"))) -> Normal
A64: O00063 | B64: 45726 | C64: C0843 | D64: {=_xlfn.XLOOKUP(C64,Customers!A:A,Customers!B:B)} -> Customer 0843 | E64: R037 | F64: {=_xlfn.XLOOKUP(E64,Restaurants!A:A,Restaurants!B:B)} -> Restaurant 037 | G64: F0207 | H64: {=_xlfn.XLOOKUP(G64,Food_Menu!A:A,Food_Menu!B:B)} -> Food Item 0207 | I64: {=_xlfn.XLOOKUP(G64,Food_Menu!A:A,Food_Menu!D:D)} -> 225.36 | J64: D140 | K64: {=_xlfn.XLOOKUP(J64,Delivery_Partners!A:A,Delivery_Partners!B:B)} -> Delivery Partner 140 | L64: 1 | M64: Delivered | N64: Cash | O64: 43 | P64: =I64*L64 -> 225.36 | Q64: =IF(O64="","Not Delivered",IF(O64<=30,"Fast",IF(O64<=60,"Normal","Slow"))) -> Normal
A65: O00064 | B65: 17/07/2025 | C65: C1082 | D65: {=_xlfn.XLOOKUP(C65,Customers!A:A,Customers!B:B)} -> Customer 1082 | E65: R064 | F65: {=_xlfn.XLOOKUP(E65,Restaurants!A:A,Restaurants!B:B)} -> Restaurant 064 | G65: F0069 | H65: {=_xlfn.XLOOKUP(G65,Food_Menu!A:A,Food_Menu!B:B)} -> Food Item 0069 | I65: {=_xlfn.XLOOKUP(G65,Food_Menu!A:A,Food_Menu!D:D)} -> 622.23 | J65: D058 | K65: {=_xlfn.XLOOKUP(J65,Delivery_Partners!A:A,Delivery_Partners!B:B)} -> Delivery Partner 058 | L65: 4 | M65: Delivered | N65: UPI | O65: 33 | P65: =I65*L65 -> 2488.92 | Q65: =IF(O65="","Not Delivered",IF(O65<=30,"Fast",IF(O65<=60,"Normal","Slow"))) -> Normal
A66: O00065 | B66: 45820 | C66: C0599 | D66: {=_xlfn.XLOOKUP(C66,Customers!A:A,Customers!B:B)} -> Customer 0599 | E66: R001 | F66: {=_xlfn.XLOOKUP(E66,Restaurants!A:A,Restaurants!B:B)} -> Restaurant 001 | G66: F0079 | H66: {=_xlfn.XLOOKUP(G66,Food_Menu!A:A,Food_Menu!B:B)} -> Food Item 0079 | J66: D101 | K66: {=_xlfn.XLOOKUP(J66,Delivery_Partners!A:A,Delivery_Partners!B:B)} -> Delivery Partner 101 | L66: 1 | M66: Cancelled | N66: UPI
A67: O00066 | B67: 29/08/2025 | C67: C0582 | D67: {=_xlfn.XLOOKUP(C67,Customers!A:A,Customers!B:B)} -> Customer 0582 | E67: R021 | F67: {=_xlfn.XLOOKUP(E67,Restaurants!A:A,Restaurants!B:B)} -> Restaurant 021 | G67: F0195 | H67: {=_xlfn.XLOOKUP(G67,Food_Menu!A:A,Food_Menu!B:B)} -> Food Item 0195 | I67: {=_xlfn.XLOOKUP(G67,Food_Menu!A:A,Food_Menu!D:D)} -> 547.24 | J67: D164 | K67: {=_xlfn.XLOOKUP(J67,Delivery_Partners!A:A,Delivery_Partners!B:B)} -> Delivery Partner 164 | L67: 1 | M67: Delivered | N67: Wallet | O67: 35 | P67: =I67*L67 -> 547.24 | Q67: =IF(O67="","Not Delivered",IF(O67<=30,"Fast",IF(O67<=60,"Normal","Slow"))) -> Normal
A68: O00067 | B68: 22/11/2025 | C68: C0515 | D68: {=_xlfn.XLOOKUP(C68,Customers!A:A,Customers!B:B)} -> Customer 0515 | E68: R095 | F68: {=_xlfn.XLOOKUP(E68,Restaurants!A:A,Restaurants!B:B)} -> Restaurant 095 | G68: F0058 | H68: {=_xlfn.XLOOKUP(G68,Food_Menu!A:A,Food_Menu!B:B)} -> Food Item 0058 | I68: {=_xlfn.XLOOKUP(G68,Food_Menu!A:A,Food_Menu!D:D)} -> 356 | J68: D163 | K68: {=_xlfn.XLOOKUP(J68,Delivery_Partners!A:A,Delivery_Partners!B:B)} -> Delivery Partner 163 | L68: 1 | M68: Delivered | N68: Card | O68: 52 | P68: =I68*L68 -> 356 | Q68: =IF(O68="","Not Delivered",IF(O68<=30,"Fast",IF(O68<=60,"Normal","Slow"))) -> Normal
A69: O00068 | B69: 24/12/2025 | C69: C0448 | D69: {=_xlfn.XLOOKUP(C69,Customers!A:A,Customers!B:B)} -> Customer 0448 | E69: R075 | F69: {=_xlfn.XLOOKUP(E69,Restaurants!A:A,Restaurants!B:B)} -> Restaurant 075 | G69: F0102 | H69: {=_xlfn.XLOOKUP(G69,Food_Menu!A:A,Food_Menu!B:B)} -> Food Item 0102 | I69: {=_xlfn.XLOOKUP(G69,Food_Menu!A:A,Food_Menu!D:D)} -> 630.13 | J69: D034 | K69: {=_xlfn.XLOOKUP(J69,Delivery_Partners!A:A,Delivery_Partners!B:B)} -> Delivery Partner 034 | L69: 1 | M69: Delivered | N69: Cash | O69: 24 | P69: =I69*L69 -> 630.13 | Q69: =IF(O69="","Not Delivered",IF(O69<=30,"Fast",IF(O69<=60,"Normal","Slow"))) -> Fast
A70: O00069 | B70: 29/12/2025 | C70: C0457 | D70: {=_xlfn.XLOOKUP(C70,Customers!A:A,Customers!B:B)} -> Customer 0457 | E70: R073 | F70: {=_xlfn.XLOOKUP(E70,Restaurants!A:A,Restaurants!B:B)} -> Restaurant 073 | G70: F0202 | H70: {=_xlfn.XLOOKUP(G70,Food_Menu!A:A,Food_Menu!B:B)} -> Food Item 0202 | J70: D085 | K70: {=_xlfn.XLOOKUP(J70,Delivery_Partners!A:A,Delivery_Partners!B:B)} -> Delivery Partner 085 | L70: 2 | M70: Cancelled | N70: Wallet
A71: O00070 | B71: 29/09/2025 | C71: C0665 | D71: {=_xlfn.XLOOKUP(C71,Customers!A:A,Customers!B:B)} -> Customer 0665 | E71: R119 | F71: {=_xlfn.XLOOKUP(E71,Restaurants!A:A,Restaurants!B:B)} -> Restaurant 119 | G71: F0070 | H71: {=_xlfn.XLOOKUP(G71,Food_Menu!A:A,Food_Menu!B:B)} -> Food Item 0070 | I71: {=_xlfn.XLOOKUP(G71,Food_Menu!A:A,Food_Menu!D:D)} -> 329.84 | J71: D052 | K71: {=_xlfn.XLOOKUP(J71,Delivery_Partners!A:A,Delivery_Partners!B:B)} -> Delivery Partner 052 | L71: 2 | M71: Delivered | N71: Cash | O71: 55 | P71: =I71*L71 -> 659.68 | Q71: =IF(O71="","Not Delivered",IF(O71<=30,"Fast",IF(O71<=60,"Normal","Slow"))) -> Normal
A72: O00071 | B72: 45846 | C72: C1075 | D72: {=_xlfn.XLOOKUP(C72,Customers!A:A,Customers!B:B)} -> Customer 1075 | E72: R028 | F72: {=_xlfn.XLOOKUP(E72,Restaurants!A:A,Restaurants!B:B)} -> Restaurant 028 | G72: F0138 | H72: {=_xlfn.XLOOKUP(G72,Food_Menu!A:A,Food_Menu!B:B)} -> Food Item 0138 | I72: {=_xlfn.XLOOKUP(G72,Food_Menu!A:A,Food_Menu!D:D)} -> 153.3 | J72: D111 | K72: {=_xlfn.XLOOKUP(J72,Delivery_Partners!A:A,Delivery_Partners!B:B)} -> Delivery Partner 111 | L72: 4 | M72: Delivered | N72: UPI | O72: 31 | P72: =I72*L72 -> 613.2 | Q72: =IF(O72="","Not Delivered",IF(O72<=30,"Fast",IF(O72<=60,"Normal","Slow"))) -> Normal
A73: O00072 | B73: 13/02/2025 | C73: C1178 | D73: {=_xlfn.XLOOKUP(C73,Customers!A:A,Customers!B:B)} -> Customer 1178 | E73: R108 | F73: {=_xlfn.XLOOKUP(E73,Restaurants!A:A,Restaurants!B:B)} -> Restaurant 108 | G73: F0009 | H73: {=_xlfn.XLOOKUP(G73,Food_Menu!A:A,Food_Menu!B:B)} -> Food Item 0009 | I73: {=_xlfn.XLOOKUP(G73,Food_Menu!A:A,Food_Menu!D:D)} -> 168.03 | J73: D149 | K73: {=_xlfn.XLOOKUP(J73,Delivery_Partners!A:A,Delivery_Partners!B:B)} -> Delivery Partner 149 | L73: 1 | M73: Delivered | N73: Card | O73: 33 | P73: =I73*L73 -> 168.03 | Q73: =IF(O73="","Not Delivered",IF(O73<=30,"Fast",IF(O73<=60,"Normal","Slow"))) -> Normal
A74: O00073 | B74: 21/05/2025 | C74: C1040 | D74: {=_xlfn.XLOOKUP(C74,Customers!A:A,Customers!B:B)} -> Customer 1040 | E74: R043 | F74: {=_xlfn.XLOOKUP(E74,Restaurants!A:A,Restaurants!B:B)} -> Restaurant 043 | G74: F0220 | H74: {=_xlfn.XLOOKUP(G74,Food_Menu!A:A,Food_Menu!B:B)} -> Food Item 0220 | J74: D058 | K74: {=_xlfn.XLOOKUP(J74,Delivery_Partners!A:A,Delivery_Partners!B:B)} -> Delivery Partner 058 | L74: 1 | M74: Cancelled | N74: Card
A75: O00074 | B75: 23/06/2025 | C75: C0144 | D75: {=_xlfn.XLOOKUP(C75,Customers!A:A,Customers!B:B)} -> Customer 0144 | E75: R111 | F75: {=_xlfn.XLOOKUP(E75,Restaurants!A:A,Restaurants!B:B)} -> Restaurant 111 | G75: F0093 | H75: {=_xlfn.XLOOKUP(G75,Food_Menu!A:A,Food_Menu!B:B)} -> Food Item 0093 | I75: {=_xlfn.XLOOKUP(G75,Food_Menu!A:A,Food_Menu!D:D)} -> 337.02 | J75: D022 | K75: {=_xlfn.XLOOKUP(J75,Delivery_Partners!A:A,Delivery_Partners!B:B)} -> Delivery Partner 022 | L75: 2 | M75: Delivered | N75: Wallet | O75: 42 | P75: =I75*L75 -> 674.04 | Q75: =IF(O75="","Not Delivered",IF(O75<=30,"Fast",IF(O75<=60,"Normal","Slow"))) -> Normal
A76: O00075 | B76: 46001 | C76: C0369 | D76: {=_xlfn.XLOOKUP(C76,Customers!A:A,Customers!B:B)} -> Customer 0369 | E76: R094 | F76: {=_xlfn.XLOOKUP(E76,Restaurants!A:A,Restaurants!B:B)} -> Restaurant 094 | G76: F0148 | H76: {=_xlfn.XLOOKUP(G76,Food_Menu!A:A,Food_Menu!B:B)} -> Food Item 0148 | I76: {=_xlfn.XLOOKUP(G76,Food_Menu!A:A,Food_Menu!D:D)} -> 405.76 | J76: D012 | K76: {=_xlfn.XLOOKUP(J76,Delivery_Partners!A:A,Delivery_Partners!B:B)} -> Delivery Partner 012 | L76: 1 | M76: Delivered | N76: UPI | O76: 26 | P76: =I76*L76 -> 405.76 | Q76: =IF(O76="","Not Delivered",IF(O76<=30,"Fast",IF(O76<=60,"Normal","Slow"))) -> Fast
A77: O00076 | B77: 45724 | C77: C0909 | D77: {=_xlfn.XLOOKUP(C77,Customers!A:A,Customers!B:B)} -> Customer 0909 | E77: R026 | F77: {=_xlfn.XLOOKUP(E77,Restaurants!A:A,Restaurants!B:B)} -> Restaurant 026 | G77: F0111 | H77: {=_xlfn.XLOOKUP(G77,Food_Menu!A:A,Food_Menu!B:B)} -> Food Item 0111 | J77: D010 | K77: {=_xlfn.XLOOKUP(J77,Delivery_Partners!A:A,Delivery_Partners!B:B)} -> Delivery Partner 010 | L77: 1 | M77: Failed | N77: Card
A78: O00077 | B78: 45936 | C78: C0655 | D78: {=_xlfn.XLOOKUP(C78,Customers!A:A,Customers!B:B)} -> Customer 0655 | E78: R026 | F78: {=_xlfn.XLOOKUP(E78,Restaurants!A:A,Restaurants!B:B)} -> Restaurant 026 | G78: F0096 | H78: {=_xlfn.XLOOKUP(G78,Food_Menu!A:A,Food_Menu!B:B)} -> Food Item 0096 | I78: {=_xlfn.XLOOKUP(G78,Food_Menu!A:A,Food_Menu!D:D)} -> 399.57 | J78: D066 | K78: {=_xlfn.XLOOKUP(J78,Delivery_Partners!A:A,Delivery_Partners!B:B)} -> Delivery Partner 066 | L78: 1 | M78: Delivered | N78: Cash | O78: 24 | P78: =I78*L78 -> 399.57 | Q78: =IF(O78="","Not Delivered",IF(O78<=30,"Fast",IF(O78<=60,"Normal","Slow"))) -> Fast
A79: O00078 | B79: 23/02/2025 | C79: C0402 | D79: {=_xlfn.XLOOKUP(C79,Customers!A:A,Customers!B:B)} -> Customer 0402 | E79: R066 | F79: {=_xlfn.XLOOKUP(E79,Restaurants!A:A,Restaurants!B:B)} -> Restaurant 066 | G79: F0090 | H79: {=_xlfn.XLOOKUP(G79,Food_Menu!A:A,Food_Menu!B:B)} -> Food Item 0090 | I79: {=_xlfn.XLOOKUP(G79,Food_Menu!A:A,Food_Menu!D:D)} -> 629.64 | J79: D174 | K79: {=_xlfn.XLOOKUP(J79,Delivery_Partners!A:A,Delivery_Partners!B:B)} -> Delivery Partner 174 | L79: 1 | M79: Delivered | N79: UPI | O79: 38 | P79: =I79*L79 -> 629.64 | Q79: =IF(O79="","Not Delivered",IF(O79<=30,"Fast",IF(O79<=60,"Normal","Slow"))) -> Normal
A80: O00079 | B80: 19/09/2025 | C80: C0374 | D80: {=_xlfn.XLOOKUP(C80,Customers!A:A,Customers!B:B)} -> Customer 0374 | E80: R061 | F80: {=_xlfn.XLOOKUP(E80,Restaurants!A:A,Restaurants!B:B)} -> Restaurant 061 | G80: F0004 | H80: {=_xlfn.XLOOKUP(G80,Food_Menu!A:A,Food_Menu!B:B)} -> Food Item 0004 | I80: {=_xlfn.XLOOKUP(G80,Food_Menu!A:A,Food_Menu!D:D)} -> 173.7 | J80: D046 | K80: {=_xlfn.XLOOKUP(J80,Delivery_Partners!A:A,Delivery_Partners!B:B)} -> Delivery Partner 046 | L80: 3 | M80: Delivered | N80: Card | O80: 16 | P80: =I80*L80 -> 521.1 | Q80: =IF(O80="","Not Delivered",IF(O80<=30,"Fast",IF(O80<=60,"Normal","Slow"))) -> Fast
A81: O00080 | B81: 45844 | C81: C0141 | D81: {=_xlfn.XLOOKUP(C81,Customers!A:A,Customers!B:B)} -> Customer 0141 | E81: R029 | F81: {=_xlfn.XLOOKUP(E81,Restaurants!A:A,Restaurants!B:B)} -> Restaurant 029 | G81: F0062 | H81: {=_xlfn.XLOOKUP(G81,Food_Menu!A:A,Food_Menu!B:B)} -> Food Item 0062 | I81: {=_xlfn.XLOOKUP(G81,Food_Menu!A:A,Food_Menu!D:D)} -> 267 | J81: D073 | K81: {=_xlfn.XLOOKUP(J81,Delivery_Partners!A:A,Delivery_Partners!B:B)} -> Delivery Partner 073 | L81: 3 | M81: Delivered | N81: UPI | O81: 18 | P81: =I81*L81 -> 801 | Q81: =IF(O81="","Not Delivered",IF(O81<=30,"Fast",IF(O81<=60,"Normal","Slow"))) -> Fast
A82: O00081 | B82: 14/01/2025 | C82: C0399 | D82: {=_xlfn.XLOOKUP(C82,Customers!A:A,Customers!B:B)} -> Customer 0399 | E82: R032 | F82: {=_xlfn.XLOOKUP(E82,Restaurants!A:A,Restaurants!B:B)} -> Restaurant 032 | G82: F0084 | H82: {=_xlfn.XLOOKUP(G82,Food_Menu!A:A,Food_Menu!B:B)} -> Food Item 0084 | J82: D122 | K82: {=_xlfn.XLOOKUP(J82,Delivery_Partners!A:A,Delivery_Partners!B:B)} -> Delivery Partner 122 | L82: 2 | M82: Cancelled | N82: UPI
A83: O00082 | B83: 14/04/2025 | C83: C0507 | D83: {=_xlfn.XLOOKUP(C83,Customers!A:A,Customers!B:B)} -> Customer 0507 | E83: R108 | F83: {=_xlfn.XLOOKUP(E83,Restaurants!A:A,Restaurants!B:B)} -> Restaurant 108 | G83: F0082 | H83: {=_xlfn.XLOOKUP(G83,Food_Menu!A:A,Food_Menu!B:B)} -> Food Item 0082 | I83: {=_xlfn.XLOOKUP(G83,Food_Menu!A:A,Food_Menu!D:D)} -> 266.68 | J83: D119 | K83: {=_xlfn.XLOOKUP(J83,Delivery_Partners!A:A,Delivery_Partners!B:B)} -> Delivery Partner 119 | L83: 1 | M83: Delivered | N83: UPI | O83: 34 | P83: =I83*L83 -> 266.68 | Q83: =IF(O83="","Not Delivered",IF(O83<=30,"Fast",IF(O83<=60,"Normal","Slow"))) -> Normal
A84: O00083 | B84: 18/11/2025 | C84: C0500 | D84: {=_xlfn.XLOOKUP(C84,Customers!A:A,Customers!B:B)} -> Customer 0500 | E84: R091 | F84: {=_xlfn.XLOOKUP(E84,Restaurants!A:A,Restaurants!B:B)} -> Restaurant 091 | G84: F0061 | H84: {=_xlfn.XLOOKUP(G84,Food_Menu!A:A,Food_Menu!B:B)} -> Food Item 0061 | I84: {=_xlfn.XLOOKUP(G84,Food_Menu!A:A,Food_Menu!D:D)} -> 538.21 | J84: D049 | K84: {=_xlfn.XLOOKUP(J84,Delivery_Partners!A:A,Delivery_Partners!B:B)} -> Delivery Partner 049 | L84: 2 | M84: Delivered | N84: Card | O84: 24 | P84: =I84*L84 -> 1076.42 | Q84: =IF(O84="","Not Delivered",IF(O84<=30,"Fast",IF(O84<=60,"Normal","Slow"))) -> Fast
A85: O00084 | B85: 13/02/2025 | C85: C0659 | D85: {=_xlfn.XLOOKUP(C85,Customers!A:A,Customers!B:B)} -> Customer 0659 | E85: R023 | F85: {=_xlfn.XLOOKUP(E85,Restaurants!A:A,Restaurants!B:B)} -> Restaurant 023 | G85: F0142 | H85: {=_xlfn.XLOOKUP(G85,Food_Menu!A:A,Food_Menu!B:B)} -> Food Item 0142 | I85: {=_xlfn.XLOOKUP(G85,Food_Menu!A:A,Food_Menu!D:D)} -> 428.17 | J85: D023 | K85: {=_xlfn.XLOOKUP(J85,Delivery_Partners!A:A,Delivery_Partners!B:B)} -> Delivery Partner 023 | L85: 2 | M85: Delivered | N85: UPI | O85: 31 | P85: =I85*L85 -> 856.34 | Q85: =IF(O85="","Not Delivered",IF(O85<=30,"Fast",IF(O85<=60,"Normal","Slow"))) -> Normal
A86: O00085 | B86: 29/05/2025 | C86: C0328 | D86: {=_xlfn.XLOOKUP(C86,Customers!A:A,Customers!B:B)} -> Customer 0328 | E86: R088 | F86: {=_xlfn.XLOOKUP(E86,Restaurants!A:A,Restaurants!B:B)} -> Restaurant 088 | G86: F0183 | H86: {=_xlfn.XLOOKUP(G86,Food_Menu!A:A,Food_Menu!B:B)} -> Food Item 0183 | J86: D029 | K86: {=_xlfn.XLOOKUP(J86,Delivery_Partners!A:A,Delivery_Partners!B:B)} -> Delivery Partner 029 | L86: 2 | M86: Failed | N86: Card
A87: O00086 | B87: 45815 | C87: C0248 | D87: {=_xlfn.XLOOKUP(C87,Customers!A:A,Customers!B:B)} -> Customer 0248 | E87: R019 | F87: {=_xlfn.XLOOKUP(E87,Restaurants!A:A,Restaurants!B:B)} -> Restaurant 019 | G87: F0197 | H87: {=_xlfn.XLOOKUP(G87,Food_Menu!A:A,Food_Menu!B:B)} -> Food Item 0197 | I87: {=_xlfn.XLOOKUP(G87,Food_Menu!A:A,Food_Menu!D:D)} -> 628.28 | J87: D040 | K87: {=_xlfn.XLOOKUP(J87,Delivery_Partners!A:A,Delivery_Partners!B:B)} -> Delivery Partner 040 | L87: 1 | M87: Delivered | N87: UPI | O87: 50 | P87: =I87*L87 -> 628.28 | Q87: =IF(O87="","Not Delivered",IF(O87<=30,"Fast",IF(O87<=60,"Normal","Slow"))) -> Normal
A88: O00087 | B88: 31/01/2025 | C88: C1066 | D88: {=_xlfn.XLOOKUP(C88,Customers!A:A,Customers!B:B)} -> Customer 1066 | E88: R054 | F88: {=_xlfn.XLOOKUP(E88,Restaurants!A:A,Restaurants!B:B)} -> Restaurant 054 | G88: F0214 | H88: {=_xlfn.XLOOKUP(G88,Food_Menu!A:A,Food_Menu!B:B)} -> Food Item 0214 | I88: {=_xlfn.XLOOKUP(G88,Food_Menu!A:A,Food_Menu!D:D)} -> 371.13 | J88: D016 | K88: {=_xlfn.XLOOKUP(J88,Delivery_Partners!A:A,Delivery_Partners!B:B)} -> Delivery Partner 016 | L88: 4 | M88: Delivered | N88: UPI | O88: 34 | P88: =I88*L88 -> 1484.52 | Q88: =IF(O88="","Not Delivered",IF(O88<=30,"Fast",IF(O88<=60,"Normal","Slow"))) -> Normal
A89: O00088 | B89: 45691 | C89: C0487 | D89: {=_xlfn.XLOOKUP(C89,Customers!A:A,Customers!B:B)} -> Customer 0487 | E89: R002 | F89: {=_xlfn.XLOOKUP(E89,Restaurants!A:A,Restaurants!B:B)} -> Restaurant 002 | G89: F0143 | H89: {=_xlfn.XLOOKUP(G89,Food_Menu!A:A,Food_Menu!B:B)} -> Food Item 0143 | I89: {=_xlfn.XLOOKUP(G89,Food_Menu!A:A,Food_Menu!D:D)} -> 248.87 | J89: D083 | K89: {=_xlfn.XLOOKUP(J89,Delivery_Partners!A:A,Delivery_Partners!B:B)} -> Delivery Partner 083 | L89: 1 | M89: Delivered | N89: UPI | O89: 45 | P89: =I89*L89 -> 248.87 | Q89: =IF(O89="","Not Delivered",IF(O89<=30,"Fast",IF(O89<=60,"Normal","Slow"))) -> Normal
A90: O00089 | B90: 45942 | C90: C0306 | D90: {=_xlfn.XLOOKUP(C90,Customers!A:A,Customers!B:B)} -> Customer 0306 | E90: R078 | F90: {=_xlfn.XLOOKUP(E90,Restaurants!A:A,Restaurants!B:B)} -> Restaurant 078 | G90: F0091 | H90: {=_xlfn.XLOOKUP(G90,Food_Menu!A:A,Food_Menu!B:B)} -> Food Item 0091 | J90: D117 | K90: {=_xlfn.XLOOKUP(J90,Delivery_Partners!A:A,Delivery_Partners!B:B)} -> Delivery Partner 117 | L90: 2 | M90: Failed | N90: Card
A91: O00090 | B91: 45755 | C91: C0763 | D91: {=_xlfn.XLOOKUP(C91,Customers!A:A,Customers!B:B)} -> Customer 0763 | E91: R022 | F91: {=_xlfn.XLOOKUP(E91,Restaurants!A:A,Restaurants!B:B)} -> Restaurant 022 | G91: F0143 | H91: {=_xlfn.XLOOKUP(G91,Food_Menu!A:A,Food_Menu!B:B)} -> Food Item 0143 | J91: D122 | K91: {=_xlfn.XLOOKUP(J91,Delivery_Partners!A:A,Delivery_Partners!B:B)} -> Delivery Partner 122 | L91: 2 | M91: Cancelled | N91: UPI
A92: O00091 | B92: 18/03/2025 | C92: C0651 | D92: {=_xlfn.XLOOKUP(C92,Customers!A:A,Customers!B:B)} -> Customer 0651 | E92: R029 | F92: {=_xlfn.XLOOKUP(E92,Restaurants!A:A,Restaurants!B:B)} -> Restaurant 029 | G92: F0030 | H92: {=_xlfn.XLOOKUP(G92,Food_Menu!A:A,Food_Menu!B:B)} -> Food Item 0030 | I92: {=_xlfn.XLOOKUP(G92,Food_Menu!A:A,Food_Menu!D:D)} -> 373.16 | J92: D164 | K92: {=_xlfn.XLOOKUP(J92,Delivery_Partners!A:A,Delivery_Partners!B:B)} -> Delivery Partner 164 | L92: 3 | M92: Delivered | N92: Card | O92: 15 | P92: =I92*L92 -> 1119.48 | Q92: =IF(O92="","Not Delivered",IF(O92<=30,"Fast",IF(O92<=60,"Normal","Slow"))) -> Fast
A93: O00092 | B93: 45719 | C93: C0692 | D93: {=_xlfn.XLOOKUP(C93,Customers!A:A,Customers!B:B)} -> Customer 0692 | E93: R023 | F93: {=_xlfn.XLOOKUP(E93,Restaurants!A:A,Restaurants!B:B)} -> Restaurant 023 | G93: F0180 | H93: {=_xlfn.XLOOKUP(G93,Food_Menu!A:A,Food_Menu!B:B)} -> Food Item 0180 | I93: {=_xlfn.XLOOKUP(G93,Food_Menu!A:A,Food_Menu!D:D)} -> 498.49 | J93: D053 | K93: {=_xlfn.XLOOKUP(J93,Delivery_Partners!A:A,Delivery_Partners!B:B)} -> Delivery Partner 053 | L93: 3 | M93: Delivered | N93: Cash | O93: 24 | P93: =I93*L93 -> 1495.47 | Q93: =IF(O93="","Not Delivered",IF(O93<=30,"Fast",IF(O93<=60,"Normal","Slow"))) -> Fast
A94: O00093 | B94: 45783 | C94: C0266 | D94: {=_xlfn.XLOOKUP(C94,Customers!A:A,Customers!B:B)} -> Customer 0266 | E94: R023 | F94: {=_xlfn.XLOOKUP(E94,Restaurants!A:A,Restaurants!B:B)} -> Restaurant 023 | G94: F0118 | H94: {=_xlfn.XLOOKUP(G94,Food_Menu!A:A,Food_Menu!B:B)} -> Food Item 0118 | I94: {=_xlfn.XLOOKUP(G94,Food_Menu!A:A,Food_Menu!D:D)} -> 301.92 | J94: D118 | K94: {=_xlfn.XLOOKUP(J94,Delivery_Partners!A:A,Delivery_Partners!B:B)} -> Delivery Partner 118 | L94: 1 | M94: Delivered | N94: Cash | O94: 16 | P94: =I94*L94 -> 301.92 | Q94: =IF(O94="","Not Delivered",IF(O94<=30,"Fast",IF(O94<=60,"Normal","Slow"))) -> Fast
A95: O00094 | B95: 22/09/2025 | C95: C0868 | D95: {=_xlfn.XLOOKUP(C95,Customers!A:A,Customers!B:B)} -> Customer 0868 | E95: R010 | F95: {=_xlfn.XLOOKUP(E95,Restaurants!A:A,Restaurants!B:B)} -> Restaurant 010 | G95: F0037 | H95: {=_xlfn.XLOOKUP(G95,Food_Menu!A:A,Food_Menu!B:B)} -> Food Item 0037 | I95: {=_xlfn.XLOOKUP(G95,Food_Menu!A:A,Food_Menu!D:D)} -> 570.62 | J95: D160 | K95: {=_xlfn.XLOOKUP(J95,Delivery_Partners!A:A,Delivery_Partners!B:B)} -> Delivery Partner 160 | L95: 2 | M95: Delivered | N95: Card | O95: 38 | P95: =I95*L95 -> 1141.24 | Q95: =IF(O95="","Not Delivered",IF(O95<=30,"Fast",IF(O95<=60,"Normal","Slow"))) -> Normal
A96: O00095 | B96: 24/09/2025 | C96: C0231 | D96: {=_xlfn.XLOOKUP(C96,Customers!A:A,Customers!B:B)} -> Customer 0231 | E96: R067 | F96: {=_xlfn.XLOOKUP(E96,Restaurants!A:A,Restaurants!B:B)} -> Restaurant 067 | G96: F0094 | H96: {=_xlfn.XLOOKUP(G96,Food_Menu!A:A,Food_Menu!B:B)} -> Food Item 0094 | I96: {=_xlfn.XLOOKUP(G96,Food_Menu!A:A,Food_Menu!D:D)} -> 556.24 | J96: D006 | K96: {=_xlfn.XLOOKUP(J96,Delivery_Partners!A:A,Delivery_Partners!B:B)} -> Delivery Partner 006 | L96: 1 | M96: Delivered | N96: Card | O96: 28 | P96: =I96*L96 -> 556.24 | Q96: =IF(O96="","Not Delivered",IF(O96<=30,"Fast",IF(O96<=60,"Normal","Slow"))) -> Fast
A97: O00096 | B97: 13/03/2025 | C97: C1004 | D97: {=_xlfn.XLOOKUP(C97,Customers!A:A,Customers!B:B)} -> Customer 1004 | E97: R105 | F97: {=_xlfn.XLOOKUP(E97,Restaurants!A:A,Restaurants!B:B)} -> Restaurant 105 | G97: F0067 | H97: {=_xlfn.XLOOKUP(G97,Food_Menu!A:A,Food_Menu!B:B)} -> Food Item 0067 | I97: {=_xlfn.XLOOKUP(G97,Food_Menu!A:A,Food_Menu!D:D)} -> 575.59 | J97: D141 | K97: {=_xlfn.XLOOKUP(J97,Delivery_Partners!A:A,Delivery_Partners!B:B)} -> Delivery Partner 141 | L97: 2 | M97: Delivered | N97: Card | O97: 40 | P97: =I97*L97 -> 1151.18 | Q97: =IF(O97="","Not Delivered",IF(O97<=30,"Fast",IF(O97<=60,"Normal","Slow"))) -> Normal
A98: O00097 | B98: 22/09/2025 | C98: C0509 | D98: {=_xlfn.XLOOKUP(C98,Customers!A:A,Customers!B:B)} -> Customer 0509 | E98: R037 | F98: {=_xlfn.XLOOKUP(E98,Restaurants!A:A,Restaurants!B:B)} -> Restaurant 037 | G98: F0077 | H98: {=_xlfn.XLOOKUP(G98,Food_Menu!A:A,Food_Menu!B:B)} -> Food Item 0077 | I98: {=_xlfn.XLOOKUP(G98,Food_Menu!A:A,Food_Menu!D:D)} -> 161.62 | J98: D016 | K98: {=_xlfn.XLOOKUP(J98,Delivery_Partners!A:A,Delivery_Partners!B:B)} -> Delivery Partner 016 | L98: 1 | M98: Delivered | N98: UPI | O98: 40 | P98: =I98*L98 -> 161.62 | Q98: =IF(O98="","Not Delivered",IF(O98<=30,"Fast",IF(O98<=60,"Normal","Slow"))) -> Normal
A99: O00098 | B99: 24/11/2025 | C99: C0491 | D99: {=_xlfn.XLOOKUP(C99,Customers!A:A,Customers!B:B)} -> Customer 0491 | E99: R094 | F99: {=_xlfn.XLOOKUP(E99,Restaurants!A:A,Restaurants!B:B)} -> Restaurant 094 | G99: F0012 | H99: {=_xlfn.XLOOKUP(G99,Food_Menu!A:A,Food_Menu!B:B)} -> Food Item 0012 | I99: {=_xlfn.XLOOKUP(G99,Food_Menu!A:A,Food_Menu!D:D)} -> 390.14 | J99: D100 | K99: {=_xlfn.XLOOKUP(J99,Delivery_Partners!A:A,Delivery_Partners!B:B)} -> Delivery Partner 100 | L99: 1 | M99: Delivered | N99: UPI | O99: 43 | P99: =I99*L99 -> 390.14 | Q99: =IF(O99="","Not Delivered",IF(O99<=30,"Fast",IF(O99<=60,"Normal","Slow"))) -> Normal
A100: O00099 | B100: 24/03/2025 | C100: C0467 | D100: {=_xlfn.XLOOKUP(C100,Customers!A:A,Customers!B:B)} -> Customer 0467 | E100: R066 | F100: {=_xlfn.XLOOKUP(E100,Restaurants!A:A,Restaurants!B:B)} -> Restaurant 066 | G100: F0004 | H100: {=_xlfn.XLOOKUP(G100,Food_Menu!A:A,Food_Menu!B:B)} -> Food Item 0004 | I100: {=_xlfn.XLOOKUP(G100,Food_Menu!A:A,Food_Menu!D:D)} -> 173.7 | J100: D150 | K100: {=_xlfn.XLOOKUP(J100,Delivery_Partners!A:A,Delivery_Partners!B:B)} -> Delivery Partner 150 | L100: 3 | M100: Delivered | N100: Wallet | O100: 24 | P100: =I100*L100 -> 521.1 | Q100: =IF(O100="","Not Delivered",IF(O100<=30,"Fast",IF(O100<=60,"Normal","Slow"))) -> Fast
...

Sheet Dashboard
B3: Total Orders | D3: Total Revenue | F3: Average Order Value (AOV) | H3: Total Items Sold
B4: 8000 | D4: 4217825.2 | F4: =D4/B4 -> 527.22815 | H4: 13368

Sheet Pivot Charts
A1: Order_Status | B1: COUNTA of Order_ID
A2: Delivered | B2: 6858
A3: Cancelled | B3: 824
A4: Failed | B4: 318
A21: Payment_Method | B21: SUM of Total Amount
A22: UPI | B22: 2187388.1
A23: Card | B23: 1009950.5
A24: Wallet | B24: 520790.98
A25: Cash | B25: 496547.14
A26: Unknown | B26: 3148.47
A40: Restaurant Name | B40: SUM of Total Amount
A41: Restaurant 029 | B41: 52155.13
A42: Restaurant 117 | B42: 49021.69
A43: Restaurant 025 | B43: 48572.38
A44: Restaurant 120 | B44: 46637.27
A45: Restaurant 073 | B45: 46199.79
A46: Restaurant 040 | B46: 44334.09
A47: Restaurant 085 | B47: 44208.11
A48: Restaurant 078 | B48: 43811.94
A49: Restaurant 079 | B49: 43801.95
A50: Restaurant 037 | B50: 43713.09
A51: Restaurant 074 | B51: 43132.69
A52: Restaurant 075 | B52: 42915.32
... A160: Restaurant 031 | B160: 19599.89
A170: Delivery Performance | B170: COUNTA of Order_ID
A171: Slow | B171: 101
A172: (blank) | B172: 1142
A173: Fast | B173: 2480
A174: Normal | B174: 4277

Sheet Pivot Tables
A1: Total Orders | B1: Total Amount2
A2: 8000 | B2: 4217825.2
A4: Orders by Order Status | D4: Top 10 Food Items by Revenue
A5: Order_Status | B5: COUNTA of Order_ID | D5: Food Name | E5: SUM of Total Amount | F5: =IFERROR(__xludf.DUMMYFUNCTION("QUERY(D3:E8502,""SELECT D,E WHERE D IS NOT NULL ORDER BY E DESC LIMIT 10"",1)"),"Food Item 0090") -> Food Item 0090 | G5: =IFERROR(__xludf.DUMMYFUNCTION("""COMPUTED_VALUE"""),47222.9999999999) -> 47223
A6: Delivered | B6: 6858 | D6: Food Item 0090 | E6: 47223 | F6: =IFERROR(__xludf.DUMMYFUNCTION("""COMPUTED_VALUE"""),"Food Item 0213") -> Food Item 0213 | G6: =IFERROR(__xludf.DUMMYFUNCTION("""COMPUTED_VALUE"""),42046.8) -> 42046.8
A7: Cancelled | B7: 824 | D7: Food Item 0213 | E7: 42046.8 | F7: =IFERROR(__xludf.DUMMYFUNCTION("""COMPUTED_VALUE"""),"Food Item 0107") -> Food Item 0107 | G7: =IFERROR(__xludf.DUMMYFUNCTION("""COMPUTED_VALUE"""),41694.36) -> 41694.36
A8: Failed | B8: 318 | D8: Food Item 0107 | E8: 41694.36 | F8: =IFERROR(__xludf.DUMMYFUNCTION("""COMPUTED_VALUE"""),"Food Item 0120") -> Food Item 0120 | G8: =IFERROR(__xludf.DUMMYFUNCTION("""COMPUTED_VALUE"""),39311.3699999999) -> 39311.37
D9: Food Item 0120 | E9: 39311.37 | F9: =IFERROR(__xludf.DUMMYFUNCTION("""COMPUTED_VALUE"""),"Food Item 0020") -> Food Item 0020 | G9: =IFERROR(__xludf.DUMMYFUNCTION("""COMPUTED_VALUE"""),39027.78) -> 39027.78
D10: Food Item 0020 | E10: 39027.78 | F10: =IFERROR(__xludf.DUMMYFUNCTION("""COMPUTED_VALUE"""),"Food Item 0066") -> Food Item 0066 | G10: =IFERROR(__xludf.DUMMYFUNCTION("""COMPUTED_VALUE"""),38920.8) -> 38920.8
A11: Revenue by Restaurant | D11: Food Item 0066 | E11: 38920.8 | F11: =IFERROR(__xludf.DUMMYFUNCTION("""COMPUTED_VALUE"""),"Food Item 0189") -> Food Item 0189 | G11: =IFERROR(__xludf.DUMMYFUNCTION("""COMPUTED_VALUE"""),38604.5099999999) -> 38604.51
A12: Restaurant Name | B12: SUM of Total Amount | D12: Food Item 0189 | E12: 38604.51 | F12: =IFERROR(__xludf.DUMMYFUNCTION("""COMPUTED_VALUE"""),"Food Item 0031") -> Food Item 0031 | G12: =IFERROR(__xludf.DUMMYFUNCTION("""COMPUTED_VALUE"""),38339.49) -> 38339.49
A13: Restaurant 029 | B13: 52155.13 | D13: Food Item 0031 | E13: 38339.49 | F13: =IFERROR(__xludf.DUMMYFUNCTION("""COMPUTED_VALUE"""),"Food Item 0197") -> Food Item 0197 | G13: =IFERROR(__xludf.DUMMYFUNCTION("""COMPUTED_VALUE"""),37696.7999999999) -> 37696.8
A14: Restaurant 117 | B14: 49021.69 | D14: Food Item 0197 | E14: 37696.8 | F14: =IFERROR(__xludf.DUMMYFUNCTION("""COMPUTED_VALUE"""),"Food Item 0037") -> Food Item 0037 | G14: =IFERROR(__xludf.DUMMYFUNCTION("""COMPUTED_VALUE"""),37660.92) -> 37660.92
A15: Restaurant 025 | B15: 48572.38 | D15: Food Item 0037 | E15: 37660.92
A16: Restaurant 120 | B16: 46637.27 | D16: Food Item 0206 | E16: 37508.07
A17: Restaurant 073 | B17: 46199.79 | D17: Food Item 0187 | E17: 37218.75
A18: Restaurant 040 | B18: 44334.09 | D18: Food Item 0159 | E18: 35742.29
A19: Restaurant 085 | B19: 44208.11 | D19: Food Item 0132 | E19: 35267.84
A20: Restaurant 078 | B20: 43811.94 | D20: Food Item 0059 | E20: 35123.41
A21: Restaurant 079 | B21: 43801.95 | D21: Food Item 0209 | E21: 34684
A22: Restaurant 037 | B22: 43713.09 | D22: Food Item 0011 | E22: 34023.38
A23: Restaurant 074 | B23: 43132.69 | D23: Food Item 0184 | E23: 33149.35
A24: Restaurant 075 | B24: 42915.32 | D24: Food Item 0151 | E24: 33038.28
A25: Restaurant 013 | B25: 42874.26 | D25: Food Item 0035 | E25: 32375.31
A26: Payment_Method | B26: SUM of Total Amount | D26: Food Item 0183 | E26: 32279
A27: UPI | B27: 2187388.1 | D27: Food Item 0028 | E27: 31601.96
A28: Card | B28: 1009950.5 | D28: Food Item 0097 | E28: 31565.16
A29: Wallet | B29: 520790.98 | D29: Food Item 0047 | E29: 31205.22
A30: Cash | B30: 496547.14 | D30: Food Item 0067 | E30: 30506.27
A31: Unknown | B31: 3148.47 | D31: Food Item 0216 | E31: 30299.4
D32: Food Item 0129 | E32: 30227.6
D33: Food Item 0199 | E33: 30037.76
D34: Food Item 0142 | E34: 29971.9
A35: Orders by Delivery Performance | D35: Food Item 0193 | E35: 29949.77
A36: Delivery Performance | B36: COUNTA of Order_ID | D36: Food Item 0158 | E36: 29894.4
A37: Normal | B37: 4277 | D37: Food Item 0075 | E37: 29436.48
A38: Fast | B38: 2480 | D38: Food Item 0185 | E38: 29418.48
A39: (blank) | B39: 1142 | D39: Food Item 0133 | E39: 28778.19
A40: Slow | B40: 101 | D40: Food Item 0173 | E40: 28504.7
D41: Food Item 0165 | E41: 28482.16
A42: Quantity Sold by Food Item | D42: Food Item 0056 | E42: 28429.73
A43: Food Name | B43: SUM of Quantity | D43: Food Item 0113 | E43: 28341.56
A44: Food Item 0159 | B44: 94 | D44: Food Item 0041 | E44: 28287.05
A45: Food Item 0107 | B45: 94 | D45: Food Item 0182 | E45: 28174.85
A46: Food Item 0023 | B46: 87 | D46: Food Item 0203 | E46: 28076.79
A47: Food Item 0142 | B47: 86 | D47: Food Item 0069 | E47: 28000.35
A48: Food Item 0189 | B48: 83 | D48: Food Item 0033 | E48: 27991.79
A49: Food Item 0187 | B49: 83 | D49: Food Item 0051 | E49: 27889.38
A50: Food Item 0164 | B50: 83 | D50: Food Item 0032 | E50: 27543
A51: Food Item 0060 | B51: 83 | D51: Food Item 0181 | E51: 27002.91
A52: Food Item 0032 | B52: 83 | D52: Food Item 0171 | E52: 26841.46
A53: Food Item 0155 | B53: 82 | D53: Food Item 0008 | E53: 26722.56
A54: Food Item 0173 | B54: 81 | D54: Food Item 0218 | E54: 26659.3
A55: Food Item 0090 | B55: 81 | D55: Food Item 0005 | E55: 26505.6
... A225: Food Item 0007 | B225: 50 | D225: Food Item 0115 | E225: 2847.78
A226: Food Item 0214 | B226: 49
A227: Food Item 0200 | B227: 49
A228: Food Item 0160 | B228: 49
A229: Food Item 0123 | B229: 49
A230: Food Item 0118 | B230: 49
A231: Food Item 0103 | B231: 49
A232: Food Item 0048 | B232: 49
A233: Food Item 0217 | B233: 48
A234: Food Item 0167 | B234: 48
A235: Food Item 0146 | B235: 48
A236: Food Item 0095 | B236: 48
A237: Food Item 0085 | B237: 48
... A263: Food Item 0115 | B263: 34
B268: Total Orders | D268: Total Revenue | F268: Average Order Value (AOV) | H268: Total Items Sold
B269: 8000 | D269: 4217825.2 | F269: =D269/B269 -> 527.22815 | H269: 13368

Sheet Customers
A1: Customer_ID | B1: Customer_Name | C1: City | D1: Customer_Segment | E1: Signup_Date
A2: C0001 | B2: Customer 0001 | C2: Delhi | D2: Premium | E2: 45842
A3: C0002 | B3: Customer 0002 | C3: Chennai | D3: Premium | E3: 45828
A4: C0003 | B4: Customer 0003 | C4: Kolkata | D4: Occasional | E4: 45491
A5: C0004 | B5: Customer 0004 | C5: Mumbai | D5: Occasional | E5: 46005
A6: C0005 | B6: Customer 0005 | C6: Hyderabad | D6: Regular | E6: 45914
A7: C0006 | B7: Customer 0006 | C7: Visakhapatnam | D7: Regular | E7: 45969
A8: C0007 | B8: Customer 0007 | C8: Delhi | D8: Occasional | E8: 45713
A9: C0008 | B9: Customer 0008 | C9: Delhi | D9: Premium | E9: 46095
A10: C0009 | B10: Customer 0009 | C10: Hyderabad | D10: Regular | E10: 45642
A11: C0010 | B11: Customer 0010 | C11: Chennai | D11: Premium | E11: 46017
A12: C0011 | B12: Customer 0011 | C12: Bengaluru | D12: Occasional | E12: 45475
A13: C0012 | B13: Customer 0012 | C13: Vijayawada | D13: Occasional | E13: 45514
... A1201: C1200 | B1201: Customer 1200 | C1201: Delhi | D1201: Premium | E1201: 45380

Sheet Restaurants
A1: Restaurant_ID | B1: Restaurant_Name | C1: City | D1: Cuisine | E1: Rating | F1: Commission_Rate
A2: R001 | B2: Restaurant 001 | C2: Delhi | D2: Desserts | E2: 4.8 | F2: 0.271
A3: R002 | B3: Restaurant 002 | C3: Mumbai | D3: Chinese | E3: 3.6 | F3: 0.171
A4: R003 | B4: Restaurant 003 | C4: Warangal | D4: Healthy | E4: 4 | F4: 0.161
A5: R004 | B5: Restaurant 004 | C5: Delhi | D5: Pizza | E5: 3.5 | F5: 0.28
A6: R005 | B6: Restaurant 005 | C6: Hyderabad | D6: Beverages | E6: 3.3 | F6: 0.235
A7: R006 | B7: Restaurant 006 | C7: Delhi | D7: Pizza | E7: 3.3 | F7: 0.128
A8: R007 | B8: Restaurant 007 | C8: Pune | D8: Mexican | E8: 4.4 | F8: 0.13
A9: R008 | B9: Restaurant 008 | C9: Hyderabad | D9: South Indian | E9: 4.7 | F9: 0.124
A10: R009 | B10: Restaurant 009 | C10: Hyderabad | D10: Indian | E10: 3.4 | F10: 0.216
A11: R010 | B11: Restaurant 010 | C11: Delhi | D11: Chinese | E11: 3.7 | F11: 0.131
A12: R011 | B12: Restaurant 011 | C12: Bengaluru | D12: Desserts | E12: 3.5 | F12: 0.269
A13: R012 | B13: Restaurant 012 | C13: Kolkata | D13: Chinese | E13: 3.2 | F13: 0.27
... A121: R120 | B121: Restaurant 120 | C121: Bengaluru | D121: Fast Food | E121: 3.2 | F121: 0.256

Sheet Food_Menu
A1: Food_ID | B1: Food_Name | C1: Category | D1: Price | E1: Cost
A2: F0001 | B2: Food Item 0001 | C2: Pizza | D2: 107.77 | E2: 72.25
A3: F0002 | B3: Food Item 0002 | C3: Beverage | D3: 89.4 | E3: 67.05
A4: F0003 | B4: Food Item 0003 | C4: Burger | D4: 349.88 | E4: 211.28
A5: F0004 | B5: Food Item 0004 | C5: Pizza | D5: 173.7 | E5: 130.27
A6: F0005 | B6: Food Item 0005 | C6: Pizza | D6: 481.92 | E6: 216.55
A7: F0006 | B7: Food Item 0006 | C7: Dessert | D7: 533.33 | E7: 170.65
A8: F0007 | B8: Food Item 0007 | C8: Main Course | D8: 210.13 | E8: 139.43
A9: F0008 | B9: Food Item 0008 | C9: Burger | D9: 417.54 | E9: 145.7
A10: F0009 | B10: Food Item 0009 | C10: Pizza | D10: 168.03 | E10: 126.02
A11: F0010 | B11: Food Item 0010 | C11: Starter | D11: 253.04 | E11: 102.73
A12: F0011 | B12: Food Item 0011 | C12: Pizza | D12: 586.61 | E12: 415.51
A13: F0012 | B13: Food Item 0012 | C13: Biryani | D13: 390.14 | E13: 164.23
... A221: F0220 | B221: Food Item 0220 | C221: Burger | D221: 194.15 | E221: 94.47

Sheet Delivery_Partners
A1: Delivery_Partner_ID | B1: Partner_Name | C1: Partner_Type | D1: Rating
A2: D001 | B2: Delivery Partner 001 | C2: Contract | D2: 3.5
A3: D002 | B3: Delivery Partner 002 | C3: Full-Time | D3: 4.1
A4: D003 | B4: Delivery Partner 003 | C4: Part-Time | D4: 3.9
A5: D004 | B5: Delivery Partner 004 | C5: Full-Time | D5: 3.9
A6: D005 | B6: Delivery Partner 005 | C6: Full-Time | D6: 4.2
A7: D006 | B7: Delivery Partner 006 | C7: Full-Time | D7: 3
A8: D007 | B8: Delivery Partner 007 | C8: Full-Time | D8: 4.8
A9: D008 | B9: Delivery Partner 008 | C9: Full-Time | D9: 3.1
A10: D009 | B10: Delivery Partner 009 | C10: Part-Time | D10: 3.9
A11: D010 | B11: Delivery Partner 010 | C11: Part-Time | D11: 3.4
A12: D011 | B12: Delivery Partner 011 | C12: Full-Time | D12: 4
A13: D012 | B13: Delivery Partner 012 | C13: Full-Time | D13: 3.6
... A181: D180 | B181: Delivery Partner 180 | C181: Full-Time | D181: 4.8
